[{"Pokemon":"Abomasnow PS+WBI/EB","Battle Rating":"938","Energy Remaining":"-700","HP Remaining":"106"},{"Pokemon":"Abomasnow (Shadow) PS+WBI/EB","Battle Rating":"925","Energy Remaining":"-600","HP Remaining":"103"},{"Pokemon":"Absol Sn+DP/Mh","Battle Rating":"958","Energy Remaining":"-400","HP Remaining":"111"},{"Pokemon":"Absol (Shadow) Sn+DP/Mh","Battle Rating":"950","Energy Remaining":"-400","HP Remaining":"109"},{"Pokemon":"Accelgor WSh+BBu/AS","Battle Rating":"975","Energy Remaining":"-500","HP Remaining":"115"},{"Pokemon":"Aerodactyl RTh+RS/EP","Battle Rating":"851","Energy Remaining":"-800","HP Remaining":"85"},{"Pokemon":"Aerodactyl (Shadow) RTh+RS/EP","Battle Rating":"876","Energy Remaining":"-700","HP Remaining":"91"},{"Pokemon":"Aggron SD+MeB/T","Battle Rating":"772","Energy Remaining":"-1500","HP Remaining":"66"},{"Pokemon":"Aggron (Shadow) SD+MeB/T","Battle Rating":"785","Energy Remaining":"-1200","HP Remaining":"69"},{"Pokemon":"Aipom Scr+AA/Re","Battle Rating":"900","Energy Remaining":"-600","HP Remaining":"97"},{"Pokemon":"Aipom (Shadow) Scr+AA/LS","Battle Rating":"896","Energy Remaining":"-500","HP Remaining":"96"},{"Pokemon":"Alakazam C+FiP/SB","Battle Rating":"958","Energy Remaining":"-400","HP Remaining":"111"},{"Pokemon":"Alakazam (Shadow) C+FiP/SB","Battle Rating":"950","Energy Remaining":"-400","HP Remaining":"109"},{"Pokemon":"Alomomola W+HP/P","Battle Rating":"888","Energy Remaining":"-900","HP Remaining":"94"},{"Pokemon":"Altaria DB+SA/M","Battle Rating":"867","Energy Remaining":"-800","HP Remaining":"89"},{"Pokemon":"Amaura PS+WBI/Tb","Battle Rating":"896","Energy Remaining":"-1000","HP Remaining":"96"},{"Pokemon":"Ambipom Scr+AA/Re","Battle Rating":"917","Energy Remaining":"-500","HP Remaining":"101"},{"Pokemon":"Ambipom (Shadow) Scr+AA/LS","Battle Rating":"896","Energy Remaining":"-500","HP Remaining":"96"},{"Pokemon":"Amoonguss FA+GK/FoP","Battle Rating":"913","Energy Remaining":"-700","HP Remaining":"100"},{"Pokemon":"Amoonguss (Shadow) FA+GK/FoP","Battle Rating":"900","Energy Remaining":"-600","HP Remaining":"97"},{"Pokemon":"Ampharos VS+TP/TBl","Battle Rating":"950","Energy Remaining":"-600","HP Remaining":"109"},{"Pokemon":"Ampharos (Shadow) VS+TP/TBl","Battle Rating":"942","Energy Remaining":"-500","HP Remaining":"107"},{"Pokemon":"Anorith StB+AP/CP","Battle Rating":"867","Energy Remaining":"-700","HP Remaining":"89"},{"Pokemon":"Anorith (Shadow) StB+AP/CP","Battle Rating":"842","Energy Remaining":"-600","HP Remaining":"83"},{"Pokemon":"Araquanid BBi+BBu/BuB","Battle Rating":"851","Energy Remaining":"-900","HP Remaining":"85"},{"Pokemon":"Arbok DT+DP/SW","Battle Rating":"917","Energy Remaining":"-600","HP Remaining":"101"},{"Pokemon":"Arbok (Shadow) DT+DP/SW","Battle Rating":"950","Energy Remaining":"-500","HP Remaining":"109"},{"Pokemon":"Arboliva ML+EP/SeB","Battle Rating":"917","Energy Remaining":"-600","HP Remaining":"101"},{"Pokemon":"Arcanine Sn+WC/PsF","Battle Rating":"942","Energy Remaining":"-600","HP Remaining":"107"},{"Pokemon":"Arcanine (Hisuian) Sn+WC/RS","Battle Rating":"942","Energy Remaining":"-800","HP Remaining":"107"},{"Pokemon":"Arcanine (Shadow) Sn+WC/PsF","Battle Rating":"966","Energy Remaining":"-500","HP Remaining":"113"},{"Pokemon":"Archen WA+AP/DC","Battle Rating":"925","Energy Remaining":"-600","HP Remaining":"103"},{"Pokemon":"Archeops WA+AP/DC","Battle Rating":"925","Energy Remaining":"-600","HP Remaining":"103"},{"Pokemon":"Arctibax DB+Av/DC","Battle Rating":"900","Energy Remaining":"-600","HP Remaining":"97"},{"Pokemon":"Ariados PSt+CP/Mh","Battle Rating":"962","Energy Remaining":"-600","HP Remaining":"112"},{"Pokemon":"Armaldo FC+RB/Li","Battle Rating":"867","Energy Remaining":"-800","HP Remaining":"89"},{"Pokemon":"Armaldo (Shadow) FC+RB/Li","Battle Rating":"884","Energy Remaining":"-700","HP Remaining":"93"},{"Pokemon":"Aromatisse Ch+M/Tb","Battle Rating":"892","Energy Remaining":"-700","HP Remaining":"95"},{"Pokemon":"Aron Tk+BS/IH","Battle Rating":"834","Energy Remaining":"-1400","HP Remaining":"81"},{"Pokemon":"Aron (Shadow) Tk+BS/IH","Battle Rating":"851","Energy Remaining":"-1300","HP Remaining":"85"},{"Pokemon":"Articuno IS+IW/AP","Battle Rating":"933","Energy Remaining":"-700","HP Remaining":"105"},{"Pokemon":"Articuno (Galarian) PC+AP/BrB","Battle Rating":"975","Energy Remaining":"-600","HP Remaining":"115"},{"Pokemon":"Articuno (Shadow) IS+IW/AP","Battle Rating":"917","Energy Remaining":"-600","HP Remaining":"101"},{"Pokemon":"Audino ZH+DV/HB","Battle Rating":"962","Energy Remaining":"-1000","HP Remaining":"112"},{"Pokemon":"Aurorus PS+WBI/MeB","Battle Rating":"896","Energy Remaining":"-1000","HP Remaining":"96"},{"Pokemon":"Avalugg IF+Av/BS","Battle Rating":"913","Energy Remaining":"-700","HP Remaining":"100"},{"Pokemon":"Axew Scr+DC/AT","Battle Rating":"917","Energy Remaining":"-500","HP Remaining":"101"},{"Pokemon":"Azelf Cf+FS/FiB","Battle Rating":"950","Energy Remaining":"-500","HP Remaining":"109"},{"Pokemon":"Azumarill B+IB/PR","Battle Rating":"938","Energy Remaining":"-1000","HP Remaining":"106"},{"Pokemon":"Banette SC+SB/T","Battle Rating":"772","Energy Remaining":"-1000","HP Remaining":"66"},{"Pokemon":"Banette (Shadow) SC+SB/T","Battle Rating":"785","Energy Remaining":"-900","HP Remaining":"69"},{"Pokemon":"Barbaracle FC+SE/CrC","Battle Rating":"888","Energy Remaining":"-900","HP Remaining":"94"},{"Pokemon":"Basculin WG+AT/MW","Battle Rating":"938","Energy Remaining":"-500","HP Remaining":"106"},{"Pokemon":"Bastiodon SD+SE/Ft","Battle Rating":"698","Energy Remaining":"-2900","HP Remaining":"48"},{"Pokemon":"Bastiodon (Shadow) SD+SE/Ft","Battle Rating":"735","Energy Remaining":"-2400","HP Remaining":"57"},{"Pokemon":"Baxcalibur DB+Av/DC","Battle Rating":"896","Energy Remaining":"-500","HP Remaining":"96"},{"Pokemon":"Bayleef RL+GK/AP","Battle Rating":"867","Energy Remaining":"-800","HP Remaining":"89"},{"Pokemon":"Bayleef (Shadow) RL+GK/AP","Battle Rating":"876","Energy Remaining":"-700","HP Remaining":"91"},{"Pokemon":"Beartic PS+IP/S","Battle Rating":"950","Energy Remaining":"-500","HP Remaining":"109"},{"Pokemon":"Beautifly Inf+SvW/AC","Battle Rating":"954","Energy Remaining":"-500","HP Remaining":"110"},{"Pokemon":"Beedrill PJ+XS/DR","Battle Rating":"913","Energy Remaining":"-600","HP Remaining":"100"},{"Pokemon":"Beedrill (Shadow) PJ+XS/DR","Battle Rating":"933","Energy Remaining":"-500","HP Remaining":"105"},{"Pokemon":"Beheeyem Cf+RS/P","Battle Rating":"958","Energy Remaining":"-500","HP Remaining":"111"},{"Pokemon":"Bellossom BS+LB/Re","Battle Rating":"958","Energy Remaining":"-700","HP Remaining":"111"},{"Pokemon":"Bellossom (Shadow) BS+LB/DG","Battle Rating":"950","Energy Remaining":"-600","HP Remaining":"109"},{"Pokemon":"Bergmite Tk+IW/Cr","Battle Rating":"925","Energy Remaining":"-600","HP Remaining":"103"},{"Pokemon":"Bewear SC+SP/St","Battle Rating":"900","Energy Remaining":"-600","HP Remaining":"97"},{"Pokemon":"Bibarel WG+S/HF","Battle Rating":"925","Energy Remaining":"-600","HP Remaining":"103"},{"Pokemon":"Bibarel (Shadow) WG+S/HF","Battle Rating":"917","Energy Remaining":"-500","HP Remaining":"101"},{"Pokemon":"Bisharp Sn+DP/XS","Battle Rating":"925","Energy Remaining":"-700","HP Remaining":"103"},{"Pokemon":"Blastoise WG+HC/IB","Battle Rating":"913","Energy Remaining":"-700","HP Remaining":"100"},{"Pokemon":"Blastoise (Shadow) WG+HC/IB","Battle Rating":"925","Energy Remaining":"-600","HP Remaining":"103"},{"Pokemon":"Blaziken C+BK/SE","Battle Rating":"950","Energy Remaining":"-500","HP Remaining":"109"},{"Pokemon":"Blaziken (Shadow) C+BK/SE","Battle Rating":"942","Energy Remaining":"-400","HP Remaining":"107"},{"Pokemon":"Blissey ZH+P/HB","Battle Rating":"950","Energy Remaining":"-1200","HP Remaining":"109"},{"Pokemon":"Boldore SD+RS/Bd","Battle Rating":"851","Energy Remaining":"-900","HP Remaining":"85"},{"Pokemon":"Bombirdier WA+Fl/Pbk","Battle Rating":"938","Energy Remaining":"-600","HP Remaining":"106"},{"Pokemon":"Bonsly C+RS/Eq","Battle Rating":"933","Energy Remaining":"-900","HP Remaining":"105"},{"Pokemon":"Bouffalant MS+St/Mh","Battle Rating":"962","Energy Remaining":"-600","HP Remaining":"112"},{"Pokemon":"Braixen E+FmC/Psh","Battle Rating":"913","Energy Remaining":"-600","HP Remaining":"100"},{"Pokemon":"Braviary AS+BrB/CC","Battle Rating":"962","Energy Remaining":"-500","HP Remaining":"112"},{"Pokemon":"Breloom C+DyP/GK","Battle Rating":"950","Energy Remaining":"-500","HP Remaining":"109"},{"Pokemon":"Brionne Ch+DV/AJ","Battle Rating":"900","Energy Remaining":"-600","HP Remaining":"97"},{"Pokemon":"Bronzong Cf+Psh/Pbk","Battle Rating":"925","Energy Remaining":"-1100","HP Remaining":"103"},{"Pokemon":"Bruxish Cf+AT/PsF","Battle Rating":"954","Energy Remaining":"-500","HP Remaining":"110"},{"Pokemon":"Bulbasaur VW+PW/SlB","Battle Rating":"938","Energy Remaining":"-600","HP Remaining":"106"},{"Pokemon":"Bulbasaur (Shadow) VW+PW/SlB","Battle Rating":"958","Energy Remaining":"-500","HP Remaining":"111"},{"Pokemon":"Buneary QA+FiP/Sw","Battle Rating":"938","Energy Remaining":"-600","HP Remaining":"106"},{"Pokemon":"Butterfree Cf+BBu/P","Battle Rating":"966","Energy Remaining":"-600","HP Remaining":"113"},{"Pokemon":"Buzzwole C+SP/Lu","Battle Rating":"938","Energy Remaining":"-600","HP Remaining":"106"},{"Pokemon":"Cacturne SkP+GK/Pbk","Battle Rating":"925","Energy Remaining":"-500","HP Remaining":"103"},{"Pokemon":"Cacturne (Shadow) SkP+GK/DP","Battle Rating":"909","Energy Remaining":"-400","HP Remaining":"99"},{"Pokemon":"Camerupt I+EP/Ov","Battle Rating":"933","Energy Remaining":"-600","HP Remaining":"105"},{"Pokemon":"Camerupt (Shadow) I+Ov/EP","Battle Rating":"921","Energy Remaining":"-500","HP Remaining":"102"},{"Pokemon":"Carbink RTh+RS/M","Battle Rating":"801","Energy Remaining":"-1700","HP Remaining":"73"},{"Pokemon":"Carnivine VW+PW/Cr","Battle Rating":"938","Energy Remaining":"-600","HP Remaining":"106"},{"Pokemon":"Carracosta WG+S/BS","Battle Rating":"888","Energy Remaining":"-900","HP Remaining":"94"},{"Pokemon":"Castform H+WBR/EB","Battle Rating":"942","Energy Remaining":"-700","HP Remaining":"107"},{"Pokemon":"Castform (Rainy) WG+WBW/T","Battle Rating":"913","Energy Remaining":"-700","HP Remaining":"100"},{"Pokemon":"Castform (Snowy) PS+WBI/Bl","Battle Rating":"938","Energy Remaining":"-700","HP Remaining":"106"},{"Pokemon":"Castform (Sunny) E+WBF/SoB","Battle Rating":"925","Energy Remaining":"-700","HP Remaining":"103"},{"Pokemon":"Celebi ML+SeB/LfS","Battle Rating":"925","Energy Remaining":"-600","HP Remaining":"103"},{"Pokemon":"Celesteela SD+BS/IH","Battle Rating":"888","Energy Remaining":"-1000","HP Remaining":"94"},{"Pokemon":"Chandelure I+FmC/SB","Battle Rating":"929","Energy Remaining":"-900","HP Remaining":"104"},{"Pokemon":"Chandelure (Shadow) I+FmC/SB","Battle Rating":"913","Energy Remaining":"-800","HP Remaining":"100"},{"Pokemon":"Chansey ZH+P/HB","Battle Rating":"950","Energy Remaining":"-1800","HP Remaining":"109"},{"Pokemon":"Charizard WA+BB/DC","Battle Rating":"938","Energy Remaining":"-600","HP Remaining":"106"},{"Pokemon":"Charizard (Shadow) WA+BB/DC","Battle Rating":"950","Energy Remaining":"-500","HP Remaining":"109"},{"Pokemon":"Charjabug VS+XS/D","Battle Rating":"954","Energy Remaining":"-700","HP Remaining":"110"},{"Pokemon":"Charmeleon E+FiP/Re","Battle Rating":"913","Energy Remaining":"-600","HP Remaining":"100"},{"Pokemon":"Charmeleon (Shadow) E+FiP/Ft","Battle Rating":"933","Energy Remaining":"-500","HP Remaining":"105"},{"Pokemon":"Chatot Pk+SA/NSh","Battle Rating":"942","Energy Remaining":"-500","HP Remaining":"107"},{"Pokemon":"Cherrim (Overcast) BS+SoB/DG","Battle Rating":"958","Energy Remaining":"-600","HP Remaining":"111"},{"Pokemon":"Cherrim (Sunshine) BS+WBF/SoB","Battle Rating":"958","Energy Remaining":"-600","HP Remaining":"111"},{"Pokemon":"Chesnaught VW+FP/SP","Battle Rating":"938","Energy Remaining":"-600","HP Remaining":"106"},{"Pokemon":"Chespin VW+BS/SeB","Battle Rating":"950","Energy Remaining":"-600","HP Remaining":"109"},{"Pokemon":"Chimecho Ex+Psh/SB","Battle Rating":"958","Energy Remaining":"-600","HP Remaining":"111"},{"Pokemon":"Chinchou Sp+Tb/BuB","Battle Rating":"938","Energy Remaining":"-600","HP Remaining":"106"},{"Pokemon":"Cinccino Ch+AT/Tb","Battle Rating":"946","Energy Remaining":"-500","HP Remaining":"108"},{"Pokemon":"Clamperl WG+BS/IB","Battle Rating":"925","Energy Remaining":"-600","HP Remaining":"103"},{"Pokemon":"Clauncher WG+Crbh/AJ","Battle Rating":"925","Energy Remaining":"-600","HP Remaining":"103"},{"Pokemon":"Clawitzer WG+Crbh/IB","Battle Rating":"938","Energy Remaining":"-500","HP Remaining":"106"},{"Pokemon":"Claydol Cf+EP/SB","Battle Rating":"933","Energy Remaining":"-800","HP Remaining":"105"},{"Pokemon":"Clefable FW+M/MM","Battle Rating":"962","Energy Remaining":"-700","HP Remaining":"112"},{"Pokemon":"Clefairy ZH+BS/DV","Battle Rating":"966","Energy Remaining":"-700","HP Remaining":"113"},{"Pokemon":"Clodsire PSt+Eq/SlB","Battle Rating":"950","Energy Remaining":"-900","HP Remaining":"109"},{"Pokemon":"Cloyster IS+IW/Li","Battle Rating":"933","Energy Remaining":"-600","HP Remaining":"105"},{"Pokemon":"Cloyster (Shadow) IS+IW/Li","Battle Rating":"917","Energy Remaining":"-600","HP Remaining":"101"},{"Pokemon":"Cofagrigus SC+SB/DP","Battle Rating":"739","Energy Remaining":"-1500","HP Remaining":"58"},{"Pokemon":"Combusken E+FmC/RS","Battle Rating":"913","Energy Remaining":"-600","HP Remaining":"100"},{"Pokemon":"Combusken (Shadow) E+FmC/RS","Battle Rating":"925","Energy Remaining":"-500","HP Remaining":"103"},{"Pokemon":"Comfey VW+GK/DK","Battle Rating":"950","Energy Remaining":"-700","HP Remaining":"109"},{"Pokemon":"Conkeldurr C+DyP/BrS","Battle Rating":"958","Energy Remaining":"-500","HP Remaining":"111"},{"Pokemon":"Corphish B+RSh/VG","Battle Rating":"971","Energy Remaining":"-500","HP Remaining":"114"},{"Pokemon":"Corsola B+RB/BuB","Battle Rating":"925","Energy Remaining":"-1100","HP Remaining":"103"},{"Pokemon":"Crabominable B+IP/Crbh","Battle Rating":"975","Energy Remaining":"-500","HP Remaining":"115"},{"Pokemon":"Crabrawler B+Crbh/PUP","Battle Rating":"975","Energy Remaining":"-500","HP Remaining":"115"},{"Pokemon":"Cradily BS+RS/GK","Battle Rating":"933","Energy Remaining":"-1200","HP Remaining":"105"},{"Pokemon":"Cradily (Shadow) BS+RS/GK","Battle Rating":"938","Energy Remaining":"-1000","HP Remaining":"106"},{"Pokemon":"Crawdaunt Sn+NS/Crbh","Battle Rating":"962","Energy Remaining":"-500","HP Remaining":"112"},{"Pokemon":"Cresselia PC+GK/M","Battle Rating":"958","Energy Remaining":"-1000","HP Remaining":"111"},{"Pokemon":"Crobat AS+PF/SB","Battle Rating":"925","Energy Remaining":"-600","HP Remaining":"103"},{"Pokemon":"Crobat (Shadow) AS+PF/SB","Battle Rating":"917","Energy Remaining":"-600","HP Remaining":"101"},{"Pokemon":"Crocalor I+Cr/Ft","Battle Rating":"942","Energy Remaining":"-600","HP Remaining":"107"},{"Pokemon":"Croconaw WG+Cr/IP","Battle Rating":"913","Energy Remaining":"-700","HP Remaining":"100"},{"Pokemon":"Croconaw (Shadow) WG+Cr/IP","Battle Rating":"900","Energy Remaining":"-600","HP Remaining":"97"},{"Pokemon":"Crustle SD+XS/RS","Battle Rating":"863","Energy Remaining":"-900","HP Remaining":"88"},{"Pokemon":"Cryogonal IS+NS/AB","Battle Rating":"933","Energy Remaining":"-700","HP Remaining":"105"},{"Pokemon":"Cubone MSl+BC/Dg","Battle Rating":"933","Energy Remaining":"-700","HP Remaining":"105"},{"Pokemon":"Cubone (Shadow) MSl+BC/Dg","Battle Rating":"925","Energy Remaining":"-600","HP Remaining":"103"},{"Pokemon":"Darmanitan (Galarian) IF+Av/SP","Battle Rating":"925","Energy Remaining":"-500","HP Remaining":"103"},{"Pokemon":"Darmanitan (Standard) I+RS/Ov","Battle Rating":"929","Energy Remaining":"-500","HP Remaining":"104"},{"Pokemon":"Dartrix L+BrB/SeB","Battle Rating":"925","Energy Remaining":"-700","HP Remaining":"103"},{"Pokemon":"Darumaka FF+FiP/FmC","Battle Rating":"900","Energy Remaining":"-600","HP Remaining":"97"},{"Pokemon":"Darumaka (Galarian) IF+IP/IB","Battle Rating":"900","Energy Remaining":"-600","HP Remaining":"97"},{"Pokemon":"Decidueye L+BrB/SS","Battle Rating":"851","Energy Remaining":"-1200","HP Remaining":"85"},{"Pokemon":"Dedenne TS+D/PR","Battle Rating":"962","Energy Remaining":"-600","HP Remaining":"112"},{"Pokemon":"Deerling Tk+WC/TBl","Battle Rating":"925","Energy Remaining":"-600","HP Remaining":"103"},{"Pokemon":"Delcatty Ch+WC/DV","Battle Rating":"909","Energy Remaining":"-700","HP Remaining":"99"},{"Pokemon":"Delphox FS+BB/MF","Battle Rating":"962","Energy Remaining":"-500","HP Remaining":"112"},{"Pokemon":"Deoxys (Defense) C+PB/Tb","Battle Rating":"933","Energy Remaining":"-800","HP Remaining":"105"},{"Pokemon":"Deoxys (Speed) CB+PB/Tb","Battle Rating":"979","Energy Remaining":"-500","HP Remaining":"116"},{"Pokemon":"Dewgong IS+IW/DR","Battle Rating":"942","Energy Remaining":"-800","HP Remaining":"107"},{"Pokemon":"Dewott FC+AT/XS","Battle Rating":"925","Energy Remaining":"-600","HP Remaining":"103"},{"Pokemon":"Diancie RTh+RS/M","Battle Rating":"867","Energy Remaining":"-900","HP Remaining":"89"},{"Pokemon":"Diggersby MS+ScS/HB","Battle Rating":"950","Energy Remaining":"-900","HP Remaining":"109"},{"Pokemon":"Dodrio FA+BrB/DrlP","Battle Rating":"925","Energy Remaining":"-500","HP Remaining":"103"},{"Pokemon":"Dolliv ML+EP/SeB","Battle Rating":"925","Energy Remaining":"-700","HP Remaining":"103"},{"Pokemon":"Donphan C+BS/Eq","Battle Rating":"950","Energy Remaining":"-600","HP Remaining":"109"},{"Pokemon":"Donphan (Shadow) C+BS/Eq","Battle Rating":"958","Energy Remaining":"-500","HP Remaining":"111"},{"Pokemon":"Dragalge DT+AT/O","Battle Rating":"900","Energy Remaining":"-700","HP Remaining":"97"},{"Pokemon":"Dragonair DB+AT/BS","Battle Rating":"900","Energy Remaining":"-600","HP Remaining":"97"},{"Pokemon":"Dragonair (Shadow) DB+BS/AT","Battle Rating":"896","Energy Remaining":"-500","HP Remaining":"96"},{"Pokemon":"Dragonite DB+DC/SP","Battle Rating":"896","Energy Remaining":"-500","HP Remaining":"96"},{"Pokemon":"Dragonite (Shadow) DB+DC/SP","Battle Rating":"896","Energy Remaining":"-500","HP Remaining":"96"},{"Pokemon":"Drapion PSt+Cr/AT","Battle Rating":"962","Energy Remaining":"-700","HP Remaining":"112"},{"Pokemon":"Drapion (Shadow) PSt+Cr/AT","Battle Rating":"950","Energy Remaining":"-600","HP Remaining":"109"},{"Pokemon":"Drifblim H+IW/SB","Battle Rating":"847","Energy Remaining":"-1500","HP Remaining":"84"},{"Pokemon":"Drifblim (Shadow) H+IW/SB","Battle Rating":"818","Energy Remaining":"-1200","HP Remaining":"77"},{"Pokemon":"Drifloon H+IW/SB","Battle Rating":"863","Energy Remaining":"-1400","HP Remaining":"88"},{"Pokemon":"Drifloon (Shadow) H+IW/SB","Battle Rating":"834","Energy Remaining":"-1200","HP Remaining":"81"},{"Pokemon":"Drilbur MSl+DR/RT","Battle Rating":"950","Energy Remaining":"-500","HP Remaining":"109"},{"Pokemon":"Drilbur (Shadow) MSl+DR/RT","Battle Rating":"942","Energy Remaining":"-500","HP Remaining":"107"},{"Pokemon":"Drowzee Cf+Psh/Re","Battle Rating":"971","Energy Remaining":"-700","HP Remaining":"114"},{"Pokemon":"Drowzee (Shadow) Cf+Psh/P","Battle Rating":"966","Energy Remaining":"-600","HP Remaining":"113"},{"Pokemon":"Druddigon DT+DC/NS","Battle Rating":"892","Energy Remaining":"-600","HP Remaining":"95"},{"Pokemon":"Dubwool DK+BS/Pbk","Battle Rating":"966","Energy Remaining":"-700","HP Remaining":"113"},{"Pokemon":"Dugtrio MS+MB/SE","Battle Rating":"966","Energy Remaining":"-500","HP Remaining":"113"},{"Pokemon":"Dugtrio (Alolan) MSl+MB/IH","Battle Rating":"892","Energy Remaining":"-700","HP Remaining":"95"},{"Pokemon":"Dugtrio (Alolan) (Shadow) MSl+MB/IH","Battle Rating":"876","Energy Remaining":"-600","HP Remaining":"91"},{"Pokemon":"Dugtrio (Shadow) SkP+MB/SE","Battle Rating":"925","Energy Remaining":"-500","HP Remaining":"103"},{"Pokemon":"Dunsparce RO+DR/RS","Battle Rating":"966","Energy Remaining":"-800","HP Remaining":"113"},{"Pokemon":"Duosion HPP+Psh/T","Battle Rating":"971","Energy Remaining":"-500","HP Remaining":"114"},{"Pokemon":"Durant BBi+XS/SE","Battle Rating":"834","Energy Remaining":"-800","HP Remaining":"81"},{"Pokemon":"Dusclops H+IP/Po","Battle Rating":"801","Energy Remaining":"-1900","HP Remaining":"73"},{"Pokemon":"Dusclops (Shadow) H+IP/Po","Battle Rating":"847","Energy Remaining":"-1500","HP Remaining":"84"},{"Pokemon":"Dusknoir H+SB/DP","Battle Rating":"851","Energy Remaining":"-1400","HP Remaining":"85"},{"Pokemon":"Dusknoir (Shadow) H+SB/DP","Battle Rating":"863","Energy Remaining":"-1100","HP Remaining":"88"},{"Pokemon":"Dustox Cf+SlB/SvW","Battle Rating":"950","Energy Remaining":"-800","HP Remaining":"109"},{"Pokemon":"Dwebble SD+XS/RB","Battle Rating":"876","Energy Remaining":"-900","HP Remaining":"91"},{"Pokemon":"Eelektrik Sp+Cr/D","Battle Rating":"925","Energy Remaining":"-600","HP Remaining":"103"},{"Pokemon":"Eelektross Sp+DC/Tb","Battle Rating":"925","Energy Remaining":"-600","HP Remaining":"103"},{"Pokemon":"Eevee QA+BS/Dg","Battle Rating":"950","Energy Remaining":"-600","HP Remaining":"109"},{"Pokemon":"Electabuzz TS+TP/Re","Battle Rating":"962","Energy Remaining":"-600","HP Remaining":"112"},{"Pokemon":"Electabuzz (Shadow) TS+TP/Tb","Battle Rating":"966","Energy Remaining":"-500","HP Remaining":"113"},{"Pokemon":"Electivire TS+IP/WC","Battle Rating":"966","Energy Remaining":"-500","HP Remaining":"113"},{"Pokemon":"Electivire (Shadow) TS+IP/WC","Battle Rating":"966","Energy Remaining":"-400","HP Remaining":"113"},{"Pokemon":"Electrode VS+D/FoP","Battle Rating":"954","Energy Remaining":"-600","HP Remaining":"110"},{"Pokemon":"Electrode (Hisuian) TS+WC/EB","Battle Rating":"962","Energy Remaining":"-600","HP Remaining":"112"},{"Pokemon":"Electrode (Shadow) VS+D/FoP","Battle Rating":"942","Energy Remaining":"-500","HP Remaining":"107"},{"Pokemon":"Elekid TS+TP/BkB","Battle Rating":"975","Energy Remaining":"-500","HP Remaining":"115"},{"Pokemon":"Elgyem Cf+DP/P","Battle Rating":"958","Energy Remaining":"-600","HP Remaining":"111"},{"Pokemon":"Emboar E+BB/RS","Battle Rating":"933","Energy Remaining":"-500","HP Remaining":"105"},{"Pokemon":"Emolga TS+Acr/D","Battle Rating":"962","Energy Remaining":"-600","HP Remaining":"112"},{"Pokemon":"Empoleon W+HC/DrlP","Battle Rating":"851","Energy Remaining":"-900","HP Remaining":"85"},{"Pokemon":"Entei FS+ScS/FmC","Battle Rating":"925","Energy Remaining":"-600","HP Remaining":"103"},{"Pokemon":"Entei (Shadow) FS+ScS/FmC","Battle Rating":"954","Energy Remaining":"-500","HP Remaining":"110"},{"Pokemon":"Escavalier C+DR/Mh","Battle Rating":"917","Energy Remaining":"-800","HP Remaining":"101"},{"Pokemon":"Espeon Cf+PsF/SB","Battle Rating":"954","Energy Remaining":"-500","HP Remaining":"110"},{"Pokemon":"Espurr Cf+Psh/EB","Battle Rating":"962","Energy Remaining":"-700","HP Remaining":"112"},{"Pokemon":"Excadrill MS+DR/RS","Battle Rating":"950","Energy Remaining":"-700","HP Remaining":"109"},{"Pokemon":"Excadrill (Shadow) MS+DR/RS","Battle Rating":"950","Energy Remaining":"-600","HP Remaining":"109"},{"Pokemon":"Exeggcute BS+SeB/AP","Battle Rating":"966","Energy Remaining":"-700","HP Remaining":"113"},{"Pokemon":"Exeggcute (Shadow) BS+SeB/AP","Battle Rating":"958","Energy Remaining":"-600","HP Remaining":"111"},{"Pokemon":"Exeggutor BS+P/SeB","Battle Rating":"975","Energy Remaining":"-500","HP Remaining":"115"},{"Pokemon":"Exeggutor (Alolan) DT+SeB/DM","Battle Rating":"946","Energy Remaining":"-500","HP Remaining":"108"},{"Pokemon":"Exeggutor (Alolan) (Shadow) DT+SeB/DM","Battle Rating":"933","Energy Remaining":"-500","HP Remaining":"105"},{"Pokemon":"Exeggutor (Shadow) BS+SeB/P","Battle Rating":"971","Energy Remaining":"-500","HP Remaining":"114"},{"Pokemon":"Exploud Bi+Cr/DV","Battle Rating":"855","Energy Remaining":"-700","HP Remaining":"86"},{"Pokemon":"Exploud (Shadow) Bi+Cr/DV","Battle Rating":"851","Energy Remaining":"-600","HP Remaining":"85"},{"Pokemon":"Falinks C+SP/Mh","Battle Rating":"938","Energy Remaining":"-600","HP Remaining":"106"},{"Pokemon":"Farfetch'd FC+LB/AA","Battle Rating":"925","Energy Remaining":"-600","HP Remaining":"103"},{"Pokemon":"Farfetch'd (Galarian) FC+LB/BrB","Battle Rating":"938","Energy Remaining":"-500","HP Remaining":"106"},{"Pokemon":"Fearow Pk+DR/AA","Battle Rating":"925","Energy Remaining":"-600","HP Remaining":"103"},{"Pokemon":"Feraligatr W+HC/Cr","Battle Rating":"909","Energy Remaining":"-600","HP Remaining":"99"},{"Pokemon":"Feraligatr (Shadow) W+HC/Cr","Battle Rating":"942","Energy Remaining":"-500","HP Remaining":"107"},{"Pokemon":"Ferroseed Tk+IH/FC","Battle Rating":"917","Energy Remaining":"-1000","HP Remaining":"101"},{"Pokemon":"Ferrothorn BS+PW/T","Battle Rating":"950","Energy Remaining":"-1100","HP Remaining":"109"},{"Pokemon":"Flaaffy Tk+D/TBl","Battle Rating":"925","Energy Remaining":"-600","HP Remaining":"103"},{"Pokemon":"Flaaffy (Shadow) CB+D/TBl","Battle Rating":"950","Energy Remaining":"-600","HP Remaining":"109"},{"Pokemon":"Flabebe VW+P/DG","Battle Rating":"950","Energy Remaining":"-600","HP Remaining":"109"},{"Pokemon":"Flareon FS+SP/Ft","Battle Rating":"958","Energy Remaining":"-500","HP Remaining":"111"},{"Pokemon":"Fletchinder E+AA/FmC","Battle Rating":"913","Energy Remaining":"-600","HP Remaining":"100"},{"Pokemon":"Floatzel W+Li/Sw","Battle Rating":"946","Energy Remaining":"-500","HP Remaining":"108"},{"Pokemon":"Floette VW+P/DG","Battle Rating":"950","Energy Remaining":"-700","HP Remaining":"109"},{"Pokemon":"Floragato L+GK/PR","Battle Rating":"925","Energy Remaining":"-600","HP Remaining":"103"},{"Pokemon":"Florges FW+DV/P","Battle Rating":"962","Energy Remaining":"-600","HP Remaining":"112"},{"Pokemon":"Flygon MS+DC/ScS","Battle Rating":"962","Energy Remaining":"-600","HP Remaining":"112"},{"Pokemon":"Flygon (Shadow) DT+DC/ScS","Battle Rating":"938","Energy Remaining":"-500","HP Remaining":"106"},{"Pokemon":"Forretress BBi+Eq/MrS","Battle Rating":"818","Energy Remaining":"-1100","HP Remaining":"77"},{"Pokemon":"Forretress (Shadow) BBi+Eq/MrS","Battle Rating":"814","Energy Remaining":"-900","HP Remaining":"76"},{"Pokemon":"Fraxure DT+DC/NS","Battle Rating":"938","Energy Remaining":"-500","HP Remaining":"106"},{"Pokemon":"Frigibax DB+Av/DC","Battle Rating":"900","Energy Remaining":"-600","HP Remaining":"97"},{"Pokemon":"Frillish H+IB/OW","Battle Rating":"863","Energy Remaining":"-1500","HP Remaining":"88"},{"Pokemon":"Frogadier B+S/AA","Battle Rating":"966","Energy Remaining":"-500","HP Remaining":"113"},{"Pokemon":"Froslass PS+Av/SB","Battle Rating":"876","Energy Remaining":"-1300","HP Remaining":"91"},{"Pokemon":"Fuecoco I+Cr/Ft","Battle Rating":"950","Energy Remaining":"-600","HP Remaining":"109"},{"Pokemon":"Furfrou SkP+S/GK","Battle Rating":"925","Energy Remaining":"-700","HP Remaining":"103"},{"Pokemon":"Furret QA+Dg/BkB","Battle Rating":"938","Energy Remaining":"-700","HP Remaining":"106"},{"Pokemon":"Gabite MS+Dg/Ft","Battle Rating":"962","Energy Remaining":"-600","HP Remaining":"112"},{"Pokemon":"Gabite (Shadow) MS+Dg/Ft","Battle Rating":"966","Energy Remaining":"-500","HP Remaining":"113"},{"Pokemon":"Gallade Cf+CC/LB","Battle Rating":"954","Energy Remaining":"-500","HP Remaining":"110"},{"Pokemon":"Gallade (Shadow) Cf+CC/LB","Battle Rating":"946","Energy Remaining":"-500","HP Remaining":"108"},{"Pokemon":"Galvantula VS+D/Lu","Battle Rating":"946","Energy Remaining":"-500","HP Remaining":"108"},{"Pokemon":"Galvantula (Shadow) VS+D/Lu","Battle Rating":"938","Energy Remaining":"-500","HP Remaining":"106"},{"Pokemon":"Garbodor Inf+BS/SeB","Battle Rating":"933","Energy Remaining":"-600","HP Remaining":"105"},{"Pokemon":"Garchomp DT+ST/O","Battle Rating":"892","Energy Remaining":"-600","HP Remaining":"95"},{"Pokemon":"Garchomp (Shadow) DT+ST/O","Battle Rating":"933","Energy Remaining":"-500","HP Remaining":"105"},{"Pokemon":"Gardevoir Ch+TAx/SB","Battle Rating":"933","Energy Remaining":"-500","HP Remaining":"105"},{"Pokemon":"Gardevoir (Shadow) Ch+TAx/SB","Battle Rating":"921","Energy Remaining":"-500","HP Remaining":"102"},{"Pokemon":"Gastrodon MSl+BS/EP","Battle Rating":"917","Energy Remaining":"-700","HP Remaining":"101"},{"Pokemon":"Genesect FC+XS/TBN","Battle Rating":"884","Energy Remaining":"-700","HP Remaining":"93"},{"Pokemon":"Gengar SC+SB/ShP","Battle Rating":"801","Energy Remaining":"-900","HP Remaining":"73"},{"Pokemon":"Gengar (Shadow) SC+SB/ShP","Battle Rating":"826","Energy Remaining":"-700","HP Remaining":"79"},{"Pokemon":"Geodude RTh+RS/Dg","Battle Rating":"867","Energy Remaining":"-800","HP Remaining":"89"},{"Pokemon":"Geodude (Alolan) VS+RS/Tb","Battle Rating":"900","Energy Remaining":"-800","HP Remaining":"97"},{"Pokemon":"Geodude (Alolan) (Shadow) VS+RS/Tb","Battle Rating":"942","Energy Remaining":"-700","HP Remaining":"107"},{"Pokemon":"Geodude (Shadow) RTh+RS/Dg","Battle Rating":"888","Energy Remaining":"-700","HP Remaining":"94"},{"Pokemon":"Gholdengo H+SB/FB","Battle Rating":"789","Energy Remaining":"-1800","HP Remaining":"70"},{"Pokemon":"Gigalith SD+SP/MeB","Battle Rating":"851","Energy Remaining":"-900","HP Remaining":"85"},{"Pokemon":"Girafarig DK+PsF/Tb","Battle Rating":"966","Energy Remaining":"-600","HP Remaining":"113"},{"Pokemon":"Girafarig (Shadow) DK+PsF/Tb","Battle Rating":"979","Energy Remaining":"-500","HP Remaining":"116"},{"Pokemon":"Glaceon IS+Av/IW","Battle Rating":"958","Energy Remaining":"-500","HP Remaining":"111"},{"Pokemon":"Glalie IS+Av/SB","Battle Rating":"933","Energy Remaining":"-700","HP Remaining":"105"},{"Pokemon":"Gligar WA+AA/Dg","Battle Rating":"917","Energy Remaining":"-800","HP Remaining":"101"},{"Pokemon":"Gligar (Shadow) WA+AA/Dg","Battle Rating":"938","Energy Remaining":"-700","HP Remaining":"106"},{"Pokemon":"Gliscor WA+Eq/AA","Battle Rating":"938","Energy Remaining":"-700","HP Remaining":"106"},{"Pokemon":"Gliscor (Shadow) WA+Eq/AA","Battle Rating":"925","Energy Remaining":"-600","HP Remaining":"103"},{"Pokemon":"Gloom RL+SlB/PlB","Battle Rating":"876","Energy Remaining":"-600","HP Remaining":"91"},{"Pokemon":"Gloom (Shadow) RL+SlB/PlB","Battle Rating":"863","Energy Remaining":"-600","HP Remaining":"88"},{"Pokemon":"Gogoat VW+LB/BkB","Battle Rating":"938","Energy Remaining":"-700","HP Remaining":"106"},{"Pokemon":"Golbat WA+PF/SB","Battle Rating":"938","Energy Remaining":"-700","HP Remaining":"106"},{"Pokemon":"Golbat (Shadow) WA+PF/SB","Battle Rating":"925","Energy Remaining":"-600","HP Remaining":"103"},{"Pokemon":"Goldeen MS+AT/HA","Battle Rating":"962","Energy Remaining":"-600","HP Remaining":"112"},{"Pokemon":"Golduck WG+CrC/Li","Battle Rating":"925","Energy Remaining":"-600","HP Remaining":"103"},{"Pokemon":"Golduck (Shadow) WG+CrC/Li","Battle Rating":"917","Energy Remaining":"-500","HP Remaining":"101"},{"Pokemon":"Golem MS+SE/Eq","Battle Rating":"950","Energy Remaining":"-900","HP Remaining":"109"},{"Pokemon":"Golem (Alolan) VS+WC/RB","Battle Rating":"900","Energy Remaining":"-900","HP Remaining":"97"},{"Pokemon":"Golem (Alolan) (Shadow) VS+SE/RB","Battle Rating":"884","Energy Remaining":"-800","HP Remaining":"93"},{"Pokemon":"Golem (Shadow) MSl+SE/Eq","Battle Rating":"892","Energy Remaining":"-800","HP Remaining":"95"},{"Pokemon":"Golett MSl+ShP/BkB","Battle Rating":"876","Energy Remaining":"-1100","HP Remaining":"91"},{"Pokemon":"Golett (Shadow) MSl+ShP/BkB","Battle Rating":"851","Energy Remaining":"-1000","HP Remaining":"85"},{"Pokemon":"Golisopod SC+XS/Li","Battle Rating":"900","Energy Remaining":"-600","HP Remaining":"97"},{"Pokemon":"Golurk MSl+ShP/EP","Battle Rating":"863","Energy Remaining":"-1100","HP Remaining":"88"},{"Pokemon":"Golurk (Shadow) MSl+ShP/EP","Battle Rating":"826","Energy Remaining":"-1000","HP Remaining":"79"},{"Pokemon":"Goodra DB+PW/MW","Battle Rating":"900","Energy Remaining":"-600","HP Remaining":"97"},{"Pokemon":"Gorebyss WG+P/WP","Battle Rating":"917","Energy Remaining":"-500","HP Remaining":"101"},{"Pokemon":"Gothitelle Cf+RS/P","Battle Rating":"962","Energy Remaining":"-700","HP Remaining":"112"},{"Pokemon":"Gothorita Cf+P/FS","Battle Rating":"962","Energy Remaining":"-700","HP Remaining":"112"},{"Pokemon":"Gourgeist (Average) H+SB/SeB","Battle Rating":"847","Energy Remaining":"-1400","HP Remaining":"84"},{"Pokemon":"Gourgeist (Large) H+SB/SeB","Battle Rating":"847","Energy Remaining":"-1500","HP Remaining":"84"},{"Pokemon":"Gourgeist (Small) H+SB/SeB","Battle Rating":"847","Energy Remaining":"-1500","HP Remaining":"84"},{"Pokemon":"Gourgeist (Super) H+SB/SeB","Battle Rating":"847","Energy Remaining":"-1400","HP Remaining":"84"},{"Pokemon":"Granbull Ch+CC/Cr","Battle Rating":"933","Energy Remaining":"-500","HP Remaining":"105"},{"Pokemon":"Granbull (Shadow) Ch+CC/Cr","Battle Rating":"921","Energy Remaining":"-500","HP Remaining":"102"},{"Pokemon":"Graveler MS+Dg/RS","Battle Rating":"950","Energy Remaining":"-900","HP Remaining":"109"},{"Pokemon":"Graveler (Alolan) VS+SE/RB","Battle Rating":"900","Energy Remaining":"-900","HP Remaining":"97"},{"Pokemon":"Graveler (Alolan) (Shadow) VS+SE/RB","Battle Rating":"884","Energy Remaining":"-800","HP Remaining":"93"},{"Pokemon":"Graveler (Shadow) MSl+Dg/RS","Battle Rating":"892","Energy Remaining":"-800","HP Remaining":"95"},{"Pokemon":"Greedent MS+BS/Cr","Battle Rating":"966","Energy Remaining":"-800","HP Remaining":"113"},{"Pokemon":"Greninja WSh+HC/NS","Battle Rating":"971","Energy Remaining":"-500","HP Remaining":"114"},{"Pokemon":"Grimer PJ+MB/SlB","Battle Rating":"913","Energy Remaining":"-600","HP Remaining":"100"},{"Pokemon":"Grimer (Alolan) PJ+Cr/SlB","Battle Rating":"913","Energy Remaining":"-600","HP Remaining":"100"},{"Pokemon":"Grimer (Alolan) (Shadow) PJ+Cr/SlB","Battle Rating":"933","Energy Remaining":"-500","HP Remaining":"105"},{"Pokemon":"Grimer (Shadow) PJ+MB/SlB","Battle Rating":"900","Energy Remaining":"-600","HP Remaining":"97"},{"Pokemon":"Grotle RL+BS/EB","Battle Rating":"888","Energy Remaining":"-700","HP Remaining":"94"},{"Pokemon":"Grotle (Shadow) RL+BS/EB","Battle Rating":"863","Energy Remaining":"-600","HP Remaining":"88"},{"Pokemon":"Grovyle QA+LB/AA","Battle Rating":"958","Energy Remaining":"-500","HP Remaining":"111"},{"Pokemon":"Grovyle (Shadow) BS+LB/AA","Battle Rating":"971","Energy Remaining":"-500","HP Remaining":"114"},{"Pokemon":"Growlithe E+BS/Ft","Battle Rating":"942","Energy Remaining":"-500","HP Remaining":"107"},{"Pokemon":"Growlithe (Hisuian) E+RS/Ft","Battle Rating":"884","Energy Remaining":"-800","HP Remaining":"93"},{"Pokemon":"Growlithe (Shadow) E+BS/Ft","Battle Rating":"933","Energy Remaining":"-500","HP Remaining":"105"},{"Pokemon":"Grumpig Ex+SB/P","Battle Rating":"958","Energy Remaining":"-700","HP Remaining":"111"},{"Pokemon":"Grumpig (Shadow) Ex+SB/P","Battle Rating":"950","Energy Remaining":"-600","HP Remaining":"109"},{"Pokemon":"Gumshoos Bi+Cr/HF","Battle Rating":"876","Energy Remaining":"-500","HP Remaining":"91"},{"Pokemon":"Gurdurr PJ+BkB/SE","Battle Rating":"925","Energy Remaining":"-600","HP Remaining":"103"},{"Pokemon":"Guzzlord DT+DC/Cr","Battle Rating":"900","Energy Remaining":"-700","HP Remaining":"97"},{"Pokemon":"Gyarados W+AT/Cr","Battle Rating":"900","Energy Remaining":"-600","HP Remaining":"97"},{"Pokemon":"Gyarados (Shadow) W+AT/Cr","Battle Rating":"942","Energy Remaining":"-500","HP Remaining":"107"},{"Pokemon":"Hakamo-o DT+DC/BkB","Battle Rating":"900","Energy Remaining":"-700","HP Remaining":"97"},{"Pokemon":"Hariyama C+CC/HS","Battle Rating":"938","Energy Remaining":"-600","HP Remaining":"106"},{"Pokemon":"Hariyama (Shadow) C+CC/HS","Battle Rating":"950","Energy Remaining":"-500","HP Remaining":"109"},{"Pokemon":"Haunter SC+IP/SB","Battle Rating":"801","Energy Remaining":"-900","HP Remaining":"73"},{"Pokemon":"Haunter (Shadow) SC+IP/SB","Battle Rating":"826","Energy Remaining":"-700","HP Remaining":"79"},{"Pokemon":"Hawlucha PJ+FlP/AA","Battle Rating":"925","Energy Remaining":"-600","HP Remaining":"103"},{"Pokemon":"Haxorus C+BkS/S","Battle Rating":"958","Energy Remaining":"-500","HP Remaining":"111"},{"Pokemon":"Heatmor FS+Ft/TP","Battle Rating":"962","Energy Remaining":"-500","HP Remaining":"112"},{"Pokemon":"Heliolisk VS+BkS/GK","Battle Rating":"946","Energy Remaining":"-500","HP Remaining":"108"},{"Pokemon":"Heracross C+CC/RB","Battle Rating":"950","Energy Remaining":"-500","HP Remaining":"109"},{"Pokemon":"Herdier L+Dg/Tb","Battle Rating":"900","Energy Remaining":"-600","HP Remaining":"97"},{"Pokemon":"Hippopotas Tk+BS/Dg","Battle Rating":"913","Energy Remaining":"-700","HP Remaining":"100"},{"Pokemon":"Hippopotas (Shadow) Tk+BS/Dg","Battle Rating":"925","Energy Remaining":"-600","HP Remaining":"103"},{"Pokemon":"Hippowdon FF+WBR/ScS","Battle Rating":"925","Energy Remaining":"-700","HP Remaining":"103"},{"Pokemon":"Hippowdon (Shadow) FF+WBR/ScS","Battle Rating":"913","Energy Remaining":"-600","HP Remaining":"100"},{"Pokemon":"Hitmonchan C+IP/TP","Battle Rating":"938","Energy Remaining":"-600","HP Remaining":"106"},{"Pokemon":"Hitmonchan (Shadow) C+IP/TP","Battle Rating":"950","Energy Remaining":"-500","HP Remaining":"109"},{"Pokemon":"Hitmonlee DK+CC/BK","Battle Rating":"975","Energy Remaining":"-500","HP Remaining":"115"},{"Pokemon":"Hitmonlee (Shadow) DK+CC/BK","Battle Rating":"971","Energy Remaining":"-400","HP Remaining":"114"},{"Pokemon":"Hitmontop C+CC/TAx","Battle Rating":"938","Energy Remaining":"-600","HP Remaining":"106"},{"Pokemon":"Hitmontop (Shadow) C+CC/TAx","Battle Rating":"925","Energy Remaining":"-600","HP Remaining":"103"},{"Pokemon":"Ho-Oh I+BrB/Eq","Battle Rating":"942","Energy Remaining":"-600","HP Remaining":"107"},{"Pokemon":"Ho-Oh (Shadow) I+BrB/Eq","Battle Rating":"929","Energy Remaining":"-500","HP Remaining":"104"},{"Pokemon":"Honchkrow Sn+BrB/DP","Battle Rating":"962","Energy Remaining":"-500","HP Remaining":"112"},{"Pokemon":"Honchkrow (Shadow) Sn+BrB/DP","Battle Rating":"954","Energy Remaining":"-400","HP Remaining":"110"},{"Pokemon":"Hoopa Cf+SB/P","Battle Rating":"909","Energy Remaining":"-1000","HP Remaining":"99"},{"Pokemon":"Houndoom Sn+Cr/Ft","Battle Rating":"962","Energy Remaining":"-500","HP Remaining":"112"},{"Pokemon":"Houndoom (Shadow) Sn+Cr/Ft","Battle Rating":"954","Energy Remaining":"-500","HP Remaining":"110"},{"Pokemon":"Houndour E+Cr/Ft","Battle Rating":"933","Energy Remaining":"-500","HP Remaining":"105"},{"Pokemon":"Houndour (Shadow) E+Cr/Ft","Battle Rating":"925","Energy Remaining":"-400","HP Remaining":"103"},{"Pokemon":"Houndstone L+PsF/SB","Battle Rating":"752","Energy Remaining":"-1300","HP Remaining":"61"},{"Pokemon":"Huntail WG+AT/Cr","Battle Rating":"925","Energy Remaining":"-600","HP Remaining":"103"},{"Pokemon":"Hydreigon DB+BrS/FC","Battle Rating":"896","Energy Remaining":"-500","HP Remaining":"96"},{"Pokemon":"Hypno Cf+SB/TP","Battle Rating":"933","Energy Remaining":"-800","HP Remaining":"105"},{"Pokemon":"Hypno (Shadow) Cf+TP/FiP","Battle Rating":"958","Energy Remaining":"-700","HP Remaining":"111"},{"Pokemon":"Illumise Tk+SvW/DG","Battle Rating":"913","Energy Remaining":"-700","HP Remaining":"100"},{"Pokemon":"Incineroar DK+DP/FmC","Battle Rating":"966","Energy Remaining":"-600","HP Remaining":"113"},{"Pokemon":"Infernape FS+CC/BB","Battle Rating":"958","Energy Remaining":"-500","HP Remaining":"111"},{"Pokemon":"Ivysaur VW+PW/SlB","Battle Rating":"938","Energy Remaining":"-700","HP Remaining":"106"},{"Pokemon":"Ivysaur (Shadow) VW+PW/SlB","Battle Rating":"925","Energy Remaining":"-600","HP Remaining":"103"},{"Pokemon":"Jellicent H+S/SB","Battle Rating":"830","Energy Remaining":"-1700","HP Remaining":"80"},{"Pokemon":"Jirachi Cf+DD/P","Battle Rating":"925","Energy Remaining":"-900","HP Remaining":"103"},{"Pokemon":"Jolteon VS+D/LR","Battle Rating":"946","Energy Remaining":"-500","HP Remaining":"108"},{"Pokemon":"Jumpluff FW+Acr/EB","Battle Rating":"966","Energy Remaining":"-900","HP Remaining":"113"},{"Pokemon":"Jumpluff (Shadow) FW+EB/Acr","Battle Rating":"950","Energy Remaining":"-800","HP Remaining":"109"},{"Pokemon":"Jynx Cf+Av/IP","Battle Rating":"954","Energy Remaining":"-500","HP Remaining":"110"},{"Pokemon":"Kabuto MS+AP/AJ","Battle Rating":"950","Energy Remaining":"-800","HP Remaining":"109"},{"Pokemon":"Kabutops MS+SE/AP","Battle Rating":"950","Energy Remaining":"-800","HP Remaining":"109"},{"Pokemon":"Kadabra PC+SB/Re","Battle Rating":"975","Energy Remaining":"-400","HP Remaining":"115"},{"Pokemon":"Kangaskhan MSl+St/Cr","Battle Rating":"933","Energy Remaining":"-700","HP Remaining":"105"},{"Pokemon":"Karrablast FC+XS/DR","Battle Rating":"917","Energy Remaining":"-500","HP Remaining":"101"},{"Pokemon":"Kartana RL+LB/NS","Battle Rating":"892","Energy Remaining":"-500","HP Remaining":"95"},{"Pokemon":"Kecleon L+FoP/Ft","Battle Rating":"884","Energy Remaining":"-700","HP Remaining":"93"},{"Pokemon":"Kingdra DB+O/Oc","Battle Rating":"900","Energy Remaining":"-600","HP Remaining":"97"},{"Pokemon":"Kingdra (Shadow) DB+O/Oc","Battle Rating":"876","Energy Remaining":"-600","HP Remaining":"91"},{"Pokemon":"Kingler MS+Crbh/XS","Battle Rating":"975","Energy Remaining":"-500","HP Remaining":"115"},{"Pokemon":"Klang TS+Tb/VG","Battle Rating":"938","Energy Remaining":"-1000","HP Remaining":"106"},{"Pokemon":"Klefki Tk+FoP/PR","Battle Rating":"888","Energy Remaining":"-900","HP Remaining":"94"},{"Pokemon":"Klinklang TS+MrS/ZC","Battle Rating":"950","Energy Remaining":"-900","HP Remaining":"109"},{"Pokemon":"Koffing Inf+DP/SlB","Battle Rating":"942","Energy Remaining":"-600","HP Remaining":"107"},{"Pokemon":"Koffing (Shadow) Inf+DP/SlB","Battle Rating":"962","Energy Remaining":"-500","HP Remaining":"112"},{"Pokemon":"Komala RO+Pbk/PR","Battle Rating":"979","Energy Remaining":"-500","HP Remaining":"116"},{"Pokemon":"Kommo-o DT+CC/DC","Battle Rating":"900","Energy Remaining":"-600","HP Remaining":"97"},{"Pokemon":"Krabby B+RSh/VG","Battle Rating":"966","Energy Remaining":"-500","HP Remaining":"113"},{"Pokemon":"Kricketune FC+XS/AA","Battle Rating":"900","Energy Remaining":"-600","HP Remaining":"97"},{"Pokemon":"Krokorok MSl+Cr/Eq","Battle Rating":"909","Energy Remaining":"-600","HP Remaining":"99"},{"Pokemon":"Krookodile Sn+Cr/Eq","Battle Rating":"933","Energy Remaining":"-600","HP Remaining":"105"},{"Pokemon":"Lairon MC+RS/BS","Battle Rating":"855","Energy Remaining":"-1500","HP Remaining":"86"},{"Pokemon":"Lairon (Shadow) MC+RS/BS","Battle Rating":"851","Energy Remaining":"-1300","HP Remaining":"85"},{"Pokemon":"Lampent E+EB/FmB","Battle Rating":"855","Energy Remaining":"-1100","HP Remaining":"86"},{"Pokemon":"Lampent (Shadow) E+EB/FmB","Battle Rating":"814","Energy Remaining":"-1000","HP Remaining":"76"},{"Pokemon":"Lanturn Sp+S/Tb","Battle Rating":"917","Energy Remaining":"-800","HP Remaining":"101"},{"Pokemon":"Lapras IS+S/SkB","Battle Rating":"942","Energy Remaining":"-800","HP Remaining":"107"},{"Pokemon":"Lapras (Shadow) IS+S/SkB","Battle Rating":"925","Energy Remaining":"-700","HP Remaining":"103"},{"Pokemon":"Larvesta E+FmC/BBu","Battle Rating":"913","Energy Remaining":"-600","HP Remaining":"100"},{"Pokemon":"Latias DB+MsB/T","Battle Rating":"900","Energy Remaining":"-600","HP Remaining":"97"},{"Pokemon":"Latias (Shadow) DB+MsB/T","Battle Rating":"896","Energy Remaining":"-500","HP Remaining":"96"},{"Pokemon":"Latios DB+DC/LrP","Battle Rating":"896","Energy Remaining":"-500","HP Remaining":"96"},{"Pokemon":"Latios (Shadow) DB+DC/LrP","Battle Rating":"896","Energy Remaining":"-500","HP Remaining":"96"},{"Pokemon":"Leafeon QA+LB/LR","Battle Rating":"950","Energy Remaining":"-600","HP Remaining":"109"},{"Pokemon":"Leavanny RL+LB/XS","Battle Rating":"876","Energy Remaining":"-600","HP Remaining":"91"},{"Pokemon":"Ledian BBi+AA/DyP","Battle Rating":"867","Energy Remaining":"-800","HP Remaining":"89"},{"Pokemon":"Ledian (Shadow) BBi+AA/DyP","Battle Rating":"855","Energy Remaining":"-700","HP Remaining":"86"},{"Pokemon":"Lickilicky L+BS/SB","Battle Rating":"867","Energy Remaining":"-800","HP Remaining":"89"},{"Pokemon":"Lickitung L+BS/PW","Battle Rating":"888","Energy Remaining":"-900","HP Remaining":"94"},{"Pokemon":"Liepard Sn+DP/PR","Battle Rating":"962","Energy Remaining":"-500","HP Remaining":"112"},{"Pokemon":"Liepard (Shadow) Sn+DP/PR","Battle Rating":"954","Energy Remaining":"-500","HP Remaining":"110"},{"Pokemon":"Lileep BS+GK/AP","Battle Rating":"933","Energy Remaining":"-1200","HP Remaining":"105"},{"Pokemon":"Lileep (Shadow) Inf+GK/AP","Battle Rating":"900","Energy Remaining":"-1000","HP Remaining":"97"},{"Pokemon":"Lilligant Ch+PlB/HB","Battle Rating":"946","Energy Remaining":"-500","HP Remaining":"108"},{"Pokemon":"Linoone SC+GK/Dg","Battle Rating":"913","Energy Remaining":"-700","HP Remaining":"100"},{"Pokemon":"Linoone (Galarian) Sn+BS/Dg","Battle Rating":"942","Energy Remaining":"-700","HP Remaining":"107"},{"Pokemon":"Litleo I+FmC/Cr","Battle Rating":"942","Energy Remaining":"-600","HP Remaining":"107"},{"Pokemon":"Lokix BBi+XS/DP","Battle Rating":"896","Energy Remaining":"-500","HP Remaining":"96"},{"Pokemon":"Lombre B+GK/IB","Battle Rating":"950","Energy Remaining":"-700","HP Remaining":"109"},{"Pokemon":"Lopunny DK+TAx/FB","Battle Rating":"966","Energy Remaining":"-700","HP Remaining":"113"},{"Pokemon":"Loudred Bi+St/DV","Battle Rating":"876","Energy Remaining":"-600","HP Remaining":"91"},{"Pokemon":"Loudred (Shadow) Bi+St/DV","Battle Rating":"876","Energy Remaining":"-500","HP Remaining":"91"},{"Pokemon":"Lucario C+PUP/SB","Battle Rating":"925","Energy Remaining":"-700","HP Remaining":"103"},{"Pokemon":"Ludicolo B+IB/LfS","Battle Rating":"942","Energy Remaining":"-700","HP Remaining":"107"},{"Pokemon":"Lugia DT+SA/A","Battle Rating":"925","Energy Remaining":"-800","HP Remaining":"103"},{"Pokemon":"Lugia (Shadow) DT+A/SA","Battle Rating":"917","Energy Remaining":"-700","HP Remaining":"101"},{"Pokemon":"Lumineon WG+SvW/Bl","Battle Rating":"913","Energy Remaining":"-700","HP Remaining":"100"},{"Pokemon":"Lunatone Cf+RS/P","Battle Rating":"925","Energy Remaining":"-900","HP Remaining":"103"},{"Pokemon":"Lurantis FC+LB/SP","Battle Rating":"925","Energy Remaining":"-600","HP Remaining":"103"},{"Pokemon":"Luxio Sp+WC/Cr","Battle Rating":"950","Energy Remaining":"-500","HP Remaining":"109"},{"Pokemon":"Luxio (Shadow) Sp+WC/Cr","Battle Rating":"933","Energy Remaining":"-500","HP Remaining":"105"},{"Pokemon":"Luxray Sp+WC/PsF","Battle Rating":"942","Energy Remaining":"-500","HP Remaining":"107"},{"Pokemon":"Luxray (Shadow) Sp+WC/PsF","Battle Rating":"933","Energy Remaining":"-500","HP Remaining":"105"},{"Pokemon":"Lycanroc (Midday) SkP+DR/SE","Battle Rating":"900","Energy Remaining":"-700","HP Remaining":"97"},{"Pokemon":"Lycanroc (Midnight) C+SE/PsF","Battle Rating":"917","Energy Remaining":"-800","HP Remaining":"101"},{"Pokemon":"Machamp C+CrC/RS","Battle Rating":"950","Energy Remaining":"-500","HP Remaining":"109"},{"Pokemon":"Machamp (Shadow) C+CrC/RS","Battle Rating":"942","Energy Remaining":"-500","HP Remaining":"107"},{"Pokemon":"Machoke KC+CrC/DyP","Battle Rating":"962","Energy Remaining":"-600","HP Remaining":"112"},{"Pokemon":"Machoke (Shadow) KC+CrC/DyP","Battle Rating":"966","Energy Remaining":"-500","HP Remaining":"113"},{"Pokemon":"Machop KC+CrC/Re","Battle Rating":"962","Energy Remaining":"-600","HP Remaining":"112"},{"Pokemon":"Machop (Shadow) KC+CrC/BkB","Battle Rating":"966","Energy Remaining":"-500","HP Remaining":"113"},{"Pokemon":"Magby KC+FiP/BkB","Battle Rating":"975","Energy Remaining":"-500","HP Remaining":"115"},{"Pokemon":"Magcargo I+RT/Ov","Battle Rating":"892","Energy Remaining":"-1100","HP Remaining":"95"},{"Pokemon":"Magmar KC+FiP/ScS","Battle Rating":"975","Energy Remaining":"-500","HP Remaining":"115"},{"Pokemon":"Magmar (Shadow) KC+FiP/ScS","Battle Rating":"966","Energy Remaining":"-500","HP Remaining":"113"},{"Pokemon":"Magmortar KC+FiP/Tb","Battle Rating":"975","Energy Remaining":"-500","HP Remaining":"115"},{"Pokemon":"Magmortar (Shadow) KC+FiP/Tb","Battle Rating":"966","Energy Remaining":"-400","HP Remaining":"113"},{"Pokemon":"Magnemite VS+MgB/D","Battle Rating":"942","Energy Remaining":"-700","HP Remaining":"107"},{"Pokemon":"Magnemite (Shadow) VS+MgB/D","Battle Rating":"933","Energy Remaining":"-600","HP Remaining":"105"},{"Pokemon":"Magneton VS+D/MgB","Battle Rating":"946","Energy Remaining":"-700","HP Remaining":"108"},{"Pokemon":"Magneton (Shadow) VS+MgB/D","Battle Rating":"933","Energy Remaining":"-600","HP Remaining":"105"},{"Pokemon":"Magnezone VS+WC/MrS","Battle Rating":"892","Energy Remaining":"-800","HP Remaining":"95"},{"Pokemon":"Magnezone (Shadow) VS+WC/MrS","Battle Rating":"938","Energy Remaining":"-700","HP Remaining":"106"},{"Pokemon":"Malamar PC+SP/FoP","Battle Rating":"975","Energy Remaining":"-700","HP Remaining":"115"},{"Pokemon":"Mamoswine PS+Av/HH","Battle Rating":"950","Energy Remaining":"-500","HP Remaining":"109"},{"Pokemon":"Mamoswine (Shadow) PS+Av/HH","Battle Rating":"942","Energy Remaining":"-500","HP Remaining":"107"},{"Pokemon":"Mandibuzz Sn+DP/AA","Battle Rating":"925","Energy Remaining":"-1000","HP Remaining":"103"},{"Pokemon":"Manectric Sn+WC/PsF","Battle Rating":"966","Energy Remaining":"-500","HP Remaining":"113"},{"Pokemon":"Manectric (Shadow) Sn+WC/PsF","Battle Rating":"962","Energy Remaining":"-400","HP Remaining":"112"},{"Pokemon":"Mankey KC+CrC/BkB","Battle Rating":"966","Energy Remaining":"-400","HP Remaining":"113"},{"Pokemon":"Mantine WA+AA/IB","Battle Rating":"933","Energy Remaining":"-800","HP Remaining":"105"},{"Pokemon":"Mantyke B+AA/IB","Battle Rating":"950","Energy Remaining":"-800","HP Remaining":"109"},{"Pokemon":"Maractus BS+AA/PlB","Battle Rating":"975","Energy Remaining":"-500","HP Remaining":"115"},{"Pokemon":"Marowak MSl+RS/BC","Battle Rating":"917","Energy Remaining":"-700","HP Remaining":"101"},{"Pokemon":"Marowak (Alolan) FS+SBo/BC","Battle Rating":"863","Energy Remaining":"-1500","HP Remaining":"88"},{"Pokemon":"Marowak (Alolan) (Shadow) FS+SBo/BC","Battle Rating":"847","Energy Remaining":"-1400","HP Remaining":"84"},{"Pokemon":"Marowak (Shadow) MSl+RS/BC","Battle Rating":"909","Energy Remaining":"-600","HP Remaining":"99"},{"Pokemon":"Marshtomp MS+S/MB","Battle Rating":"962","Energy Remaining":"-700","HP Remaining":"112"},{"Pokemon":"Marshtomp (Shadow) MS+S/MB","Battle Rating":"950","Energy Remaining":"-600","HP Remaining":"109"},{"Pokemon":"Masquerain AS+BuB/Lu","Battle Rating":"925","Energy Remaining":"-600","HP Remaining":"103"},{"Pokemon":"Mawile FF+PUP/PR","Battle Rating":"884","Energy Remaining":"-900","HP Remaining":"93"},{"Pokemon":"Mawile (Shadow) FF+PUP/PR","Battle Rating":"867","Energy Remaining":"-800","HP Remaining":"89"},{"Pokemon":"Medicham C+IP/P","Battle Rating":"933","Energy Remaining":"-800","HP Remaining":"105"},{"Pokemon":"Meganium VW+FP/Eq","Battle Rating":"938","Energy Remaining":"-700","HP Remaining":"106"},{"Pokemon":"Meganium (Shadow) VW+FP/Eq","Battle Rating":"938","Energy Remaining":"-600","HP Remaining":"106"},{"Pokemon":"Melmetal TS+SP/RS","Battle Rating":"950","Energy Remaining":"-900","HP Remaining":"109"},{"Pokemon":"Meltan TS+Tb/FC","Battle Rating":"962","Energy Remaining":"-700","HP Remaining":"112"},{"Pokemon":"Meowscarada L+NS/GK","Battle Rating":"942","Energy Remaining":"-500","HP Remaining":"107"},{"Pokemon":"Meowstic (Female) Cf+SB/P","Battle Rating":"962","Energy Remaining":"-700","HP Remaining":"112"},{"Pokemon":"Meowstic (Male) Cf+P/EB","Battle Rating":"962","Energy Remaining":"-700","HP Remaining":"112"},{"Pokemon":"Mesprit Cf+FS/Bl","Battle Rating":"958","Energy Remaining":"-600","HP Remaining":"111"},{"Pokemon":"Metagross BP+MM/P","Battle Rating":"900","Energy Remaining":"-800","HP Remaining":"97"},{"Pokemon":"Metagross (Shadow) BP+MM/P","Battle Rating":"900","Energy Remaining":"-700","HP Remaining":"97"},{"Pokemon":"Metang MC+Psh/GB","Battle Rating":"896","Energy Remaining":"-1100","HP Remaining":"96"},{"Pokemon":"Metang (Shadow) MC+Psh/GB","Battle Rating":"917","Energy Remaining":"-900","HP Remaining":"101"},{"Pokemon":"Mew SC+WC/S","Battle Rating":"900","Energy Remaining":"-600","HP Remaining":"97"},{"Pokemon":"Mewtwo (Shadow) PC+Pst/Tb","Battle Rating":"975","Energy Remaining":"-400","HP Remaining":"115"},{"Pokemon":"Mienfoo LK+BkB/FB","Battle Rating":"975","Energy Remaining":"-500","HP Remaining":"115"},{"Pokemon":"Mienshao PJ+BkB/GK","Battle Rating":"942","Energy Remaining":"-400","HP Remaining":"107"},{"Pokemon":"Mightyena IF+Cr/PF","Battle Rating":"913","Energy Remaining":"-600","HP Remaining":"100"},{"Pokemon":"Mightyena (Shadow) IF+Cr/PF","Battle Rating":"933","Energy Remaining":"-500","HP Remaining":"105"},{"Pokemon":"Milotic DT+S/Bl","Battle Rating":"917","Energy Remaining":"-700","HP Remaining":"101"},{"Pokemon":"Miltank RO+BS/Tb","Battle Rating":"966","Energy Remaining":"-800","HP Remaining":"113"},{"Pokemon":"Minun Sp+Tb/GK","Battle Rating":"925","Energy Remaining":"-700","HP Remaining":"103"},{"Pokemon":"Misdreavus H+DP/SS","Battle Rating":"847","Energy Remaining":"-1400","HP Remaining":"84"},{"Pokemon":"Misdreavus (Shadow) H+DP/SS","Battle Rating":"818","Energy Remaining":"-1200","HP Remaining":"77"},{"Pokemon":"Mismagius H+SB/DP","Battle Rating":"834","Energy Remaining":"-1200","HP Remaining":"81"},{"Pokemon":"Mismagius (Shadow) H+SB/DP","Battle Rating":"851","Energy Remaining":"-1000","HP Remaining":"85"},{"Pokemon":"Moltres WA+SA/Ov","Battle Rating":"950","Energy Remaining":"-500","HP Remaining":"109"},{"Pokemon":"Moltres (Galarian) WA+AP/BrB","Battle Rating":"938","Energy Remaining":"-700","HP Remaining":"106"},{"Pokemon":"Moltres (Shadow) WA+SA/Ov","Battle Rating":"942","Energy Remaining":"-500","HP Remaining":"107"},{"Pokemon":"Monferno E+Ft/LS","Battle Rating":"913","Energy Remaining":"-600","HP Remaining":"100"},{"Pokemon":"Mothim BBi+AA/BBu","Battle Rating":"896","Energy Remaining":"-500","HP Remaining":"96"},{"Pokemon":"Mr. Mime Cf+SB/P","Battle Rating":"958","Energy Remaining":"-600","HP Remaining":"111"},{"Pokemon":"Mr. Mime (Galarian) Cf+TAx/IP","Battle Rating":"958","Energy Remaining":"-600","HP Remaining":"111"},{"Pokemon":"Mr. Rime Cf+IW/P","Battle Rating":"958","Energy Remaining":"-600","HP Remaining":"111"},{"Pokemon":"Muk PJ+TP/DP","Battle Rating":"913","Energy Remaining":"-700","HP Remaining":"100"},{"Pokemon":"Muk (Alolan) PJ+DP/AS","Battle Rating":"913","Energy Remaining":"-700","HP Remaining":"100"},{"Pokemon":"Muk (Alolan) (Shadow) PJ+DP/AS","Battle Rating":"900","Energy Remaining":"-600","HP Remaining":"97"},{"Pokemon":"Muk (Shadow) PJ+TP/DP","Battle Rating":"900","Energy Remaining":"-600","HP Remaining":"97"},{"Pokemon":"Munchlax Tk+BS/Bd","Battle Rating":"900","Energy Remaining":"-800","HP Remaining":"97"},{"Pokemon":"Munna CB+Psh/DG","Battle Rating":"966","Energy Remaining":"-600","HP Remaining":"113"},{"Pokemon":"Murkrow FA+DrlP/FoP","Battle Rating":"909","Energy Remaining":"-500","HP Remaining":"99"},{"Pokemon":"Murkrow (Shadow) FA+DrlP/FoP","Battle Rating":"892","Energy Remaining":"-400","HP Remaining":"95"},{"Pokemon":"Musharna CB+Psh/DG","Battle Rating":"966","Energy Remaining":"-700","HP Remaining":"113"},{"Pokemon":"Nidoking DK+ST/EP","Battle Rating":"958","Energy Remaining":"-600","HP Remaining":"111"},{"Pokemon":"Nidoking (Shadow) DK+ST/EP","Battle Rating":"979","Energy Remaining":"-500","HP Remaining":"116"},{"Pokemon":"Nidoqueen PJ+EP/PF","Battle Rating":"913","Energy Remaining":"-700","HP Remaining":"100"},{"Pokemon":"Nidoqueen (Shadow) PJ+EP/PF","Battle Rating":"900","Energy Remaining":"-600","HP Remaining":"97"},{"Pokemon":"Nidorina PSt+PF/Re","Battle Rating":"962","Energy Remaining":"-700","HP Remaining":"112"},{"Pokemon":"Nidorina (Shadow) PSt+Dg/PF","Battle Rating":"962","Energy Remaining":"-600","HP Remaining":"112"},{"Pokemon":"Nidorino PJ+Dg/SlB","Battle Rating":"913","Energy Remaining":"-600","HP Remaining":"100"},{"Pokemon":"Nidorino (Shadow) PJ+Dg/SlB","Battle Rating":"933","Energy Remaining":"-500","HP Remaining":"105"},{"Pokemon":"Ninetales FS+WBF/ScS","Battle Rating":"933","Energy Remaining":"-700","HP Remaining":"105"},{"Pokemon":"Ninetales (Alolan) PS+WBI/DG","Battle Rating":"938","Energy Remaining":"-700","HP Remaining":"106"},{"Pokemon":"Ninetales (Alolan) (Shadow) PS+WBI/DG","Battle Rating":"925","Energy Remaining":"-600","HP Remaining":"103"},{"Pokemon":"Ninetales (Shadow) E+WBF/ScS","Battle Rating":"900","Energy Remaining":"-600","HP Remaining":"97"},{"Pokemon":"Ninjask FC+AA/SB","Battle Rating":"917","Energy Remaining":"-500","HP Remaining":"101"},{"Pokemon":"Noctowl WA+SA/SB","Battle Rating":"933","Energy Remaining":"-800","HP Remaining":"105"},{"Pokemon":"Noivern AS+Hu/P","Battle Rating":"925","Energy Remaining":"-600","HP Remaining":"103"},{"Pokemon":"Nosepass Sp+RS/RB","Battle Rating":"917","Energy Remaining":"-1100","HP Remaining":"101"},{"Pokemon":"Nosepass (Shadow) Sp+RS/RB","Battle Rating":"917","Energy Remaining":"-1000","HP Remaining":"101"},{"Pokemon":"Nuzleaf FA+LB/FoP","Battle Rating":"925","Energy Remaining":"-500","HP Remaining":"103"},{"Pokemon":"Nuzleaf (Shadow) FA+LB/FoP","Battle Rating":"909","Energy Remaining":"-500","HP Remaining":"99"},{"Pokemon":"Obstagoon C+NS/CrC","Battle Rating":"950","Energy Remaining":"-700","HP Remaining":"109"},{"Pokemon":"Octillery LO+Oc/GS","Battle Rating":"975","Energy Remaining":"-600","HP Remaining":"115"},{"Pokemon":"Oddish RL+SeB/SlB","Battle Rating":"876","Energy Remaining":"-600","HP Remaining":"91"},{"Pokemon":"Oddish (Shadow) RL+SeB/SlB","Battle Rating":"909","Energy Remaining":"-500","HP Remaining":"99"},{"Pokemon":"Oinkologne Tk+BS/Dg","Battle Rating":"913","Energy Remaining":"-700","HP Remaining":"100"},{"Pokemon":"Oinkologne (Female) Tk+BS/Dg","Battle Rating":"913","Energy Remaining":"-700","HP Remaining":"100"},{"Pokemon":"Omanyte MS+RB/AP","Battle Rating":"950","Energy Remaining":"-800","HP Remaining":"109"},{"Pokemon":"Omanyte (Shadow) MS+RB/AP","Battle Rating":"962","Energy Remaining":"-700","HP Remaining":"112"},{"Pokemon":"Omastar MS+RS/HP","Battle Rating":"950","Energy Remaining":"-900","HP Remaining":"109"},{"Pokemon":"Omastar (Shadow) MS+RS/HP","Battle Rating":"962","Energy Remaining":"-700","HP Remaining":"112"},{"Pokemon":"Onix RTh+BkS/RS","Battle Rating":"876","Energy Remaining":"-1200","HP Remaining":"91"},{"Pokemon":"Onix (Shadow) RTh+BkS/RS","Battle Rating":"876","Energy Remaining":"-1100","HP Remaining":"91"},{"Pokemon":"Oranguru Cf+FoP/FS","Battle Rating":"962","Energy Remaining":"-700","HP Remaining":"112"},{"Pokemon":"Oricorio (Baile) AS+AA/Hu","Battle Rating":"925","Energy Remaining":"-600","HP Remaining":"103"},{"Pokemon":"Oricorio (Pa'u) AS+AA/Hu","Battle Rating":"925","Energy Remaining":"-600","HP Remaining":"103"},{"Pokemon":"Oricorio (Pom-Pom) AS+AA/Hu","Battle Rating":"925","Energy Remaining":"-600","HP Remaining":"103"},{"Pokemon":"Oricorio (Sensu) AS+AA/Hu","Battle Rating":"851","Energy Remaining":"-1200","HP Remaining":"85"},{"Pokemon":"Overqwil PJ+AT/SB","Battle Rating":"913","Energy Remaining":"-600","HP Remaining":"100"},{"Pokemon":"Pachirisu VS+TP/Tb","Battle Rating":"925","Energy Remaining":"-900","HP Remaining":"103"},{"Pokemon":"Palossand MS+ScS/SB","Battle Rating":"913","Energy Remaining":"-1500","HP Remaining":"100"},{"Pokemon":"Palpitoad MS+EP/SW","Battle Rating":"962","Energy Remaining":"-700","HP Remaining":"112"},{"Pokemon":"Pancham Tk+BS/Cr","Battle Rating":"925","Energy Remaining":"-600","HP Remaining":"103"},{"Pokemon":"Pangoro Sn+CC/NS","Battle Rating":"933","Energy Remaining":"-600","HP Remaining":"105"},{"Pokemon":"Parasect FC+XS/CP","Battle Rating":"925","Energy Remaining":"-600","HP Remaining":"103"},{"Pokemon":"Passimian C+CC/BkB","Battle Rating":"938","Energy Remaining":"-600","HP Remaining":"106"},{"Pokemon":"Pawmo Sp+WC/D","Battle Rating":"942","Energy Remaining":"-500","HP Remaining":"107"},{"Pokemon":"Pawmot Sp+CC/WC","Battle Rating":"942","Energy Remaining":"-500","HP Remaining":"107"},{"Pokemon":"Pawniard FC+NS/XS","Battle Rating":"900","Energy Remaining":"-800","HP Remaining":"97"},{"Pokemon":"Pelipper WA+WBW/Hu","Battle Rating":"938","Energy Remaining":"-600","HP Remaining":"106"},{"Pokemon":"Perrserker SC+CC/FoP","Battle Rating":"867","Energy Remaining":"-800","HP Remaining":"89"},{"Pokemon":"Persian FA+NS/Re","Battle Rating":"900","Energy Remaining":"-600","HP Remaining":"97"},{"Pokemon":"Persian (Alolan) FA+FoP/PR","Battle Rating":"888","Energy Remaining":"-600","HP Remaining":"94"},{"Pokemon":"Persian (Shadow) FA+NS/PR","Battle Rating":"888","Energy Remaining":"-600","HP Remaining":"94"},{"Pokemon":"Phanpy Tk+BS/RS","Battle Rating":"942","Energy Remaining":"-700","HP Remaining":"107"},{"Pokemon":"Phanpy (Shadow) Tk+BS/RS","Battle Rating":"925","Energy Remaining":"-600","HP Remaining":"103"},{"Pokemon":"Pidgeot WA+FrD/BrB","Battle Rating":"938","Energy Remaining":"-700","HP Remaining":"106"},{"Pokemon":"Pidgeotto WA+AA/Tw","Battle Rating":"938","Energy Remaining":"-600","HP Remaining":"106"},{"Pokemon":"Pignite E+FmC/RT","Battle Rating":"913","Energy Remaining":"-600","HP Remaining":"100"},{"Pokemon":"Piloswine PS+Av/HH","Battle Rating":"938","Energy Remaining":"-600","HP Remaining":"106"},{"Pokemon":"Piloswine (Shadow) PS+Av/HH","Battle Rating":"925","Energy Remaining":"-600","HP Remaining":"103"},{"Pokemon":"Pineco BBi+RT/Re","Battle Rating":"900","Energy Remaining":"-600","HP Remaining":"97"},{"Pokemon":"Pineco (Shadow) BBi+RT/ST","Battle Rating":"896","Energy Remaining":"-500","HP Remaining":"96"},{"Pokemon":"Pinsir FC+CC/XS","Battle Rating":"917","Energy Remaining":"-500","HP Remaining":"101"},{"Pokemon":"Pinsir (Shadow) FC+CC/XS","Battle Rating":"896","Energy Remaining":"-500","HP Remaining":"96"},{"Pokemon":"Piplup B+DrlP/IW","Battle Rating":"950","Energy Remaining":"-600","HP Remaining":"109"},{"Pokemon":"Plusle Sp+Tb/GK","Battle Rating":"925","Energy Remaining":"-600","HP Remaining":"103"},{"Pokemon":"Politoed MS+WBW/Eq","Battle Rating":"962","Energy Remaining":"-700","HP Remaining":"112"},{"Pokemon":"Politoed (Shadow) MS+WBW/Eq","Battle Rating":"962","Energy Remaining":"-600","HP Remaining":"112"},{"Pokemon":"Poliwhirl MS+Sc/MB","Battle Rating":"962","Energy Remaining":"-700","HP Remaining":"112"},{"Pokemon":"Poliwhirl (Shadow) MS+Sc/MB","Battle Rating":"962","Energy Remaining":"-600","HP Remaining":"112"},{"Pokemon":"Poliwrath C+Sc/IP","Battle Rating":"938","Energy Remaining":"-700","HP Remaining":"106"},{"Pokemon":"Poliwrath (Shadow) C+PUP/IP","Battle Rating":"925","Energy Remaining":"-600","HP Remaining":"103"},{"Pokemon":"Ponyta E+FmC/St","Battle Rating":"933","Energy Remaining":"-500","HP Remaining":"105"},{"Pokemon":"Ponyta (Galarian) PC+PR/Psb","Battle Rating":"983","Energy Remaining":"-500","HP Remaining":"117"},{"Pokemon":"Popplio WG+AT/AJ","Battle Rating":"925","Energy Remaining":"-600","HP Remaining":"103"},{"Pokemon":"Porygon QA+D/HB","Battle Rating":"938","Energy Remaining":"-600","HP Remaining":"106"},{"Pokemon":"Porygon (Shadow) Tk+D/SiB","Battle Rating":"900","Energy Remaining":"-600","HP Remaining":"97"},{"Pokemon":"Porygon-Z LO+TA/ZC","Battle Rating":"958","Energy Remaining":"-500","HP Remaining":"111"},{"Pokemon":"Porygon-Z (Shadow) LO+TA/ZC","Battle Rating":"966","Energy Remaining":"-400","HP Remaining":"113"},{"Pokemon":"Porygon2 LO+TA/ZC","Battle Rating":"975","Energy Remaining":"-600","HP Remaining":"115"},{"Pokemon":"Porygon2 (Shadow) LO+TA/ZC","Battle Rating":"958","Energy Remaining":"-500","HP Remaining":"111"},{"Pokemon":"Primarina Ch+DV/HP","Battle Rating":"876","Energy Remaining":"-600","HP Remaining":"91"},{"Pokemon":"Primeape C+IP/CC","Battle Rating":"950","Energy Remaining":"-500","HP Remaining":"109"},{"Pokemon":"Prinplup B+IW/HP","Battle Rating":"942","Energy Remaining":"-600","HP Remaining":"107"},{"Pokemon":"Probopass Sp+RS/ZC","Battle Rating":"830","Energy Remaining":"-2100","HP Remaining":"80"},{"Pokemon":"Probopass (Shadow) Sp+RS/ZC","Battle Rating":"851","Energy Remaining":"-1600","HP Remaining":"85"},{"Pokemon":"Pumpkaboo (Average) RL+GK/FoP","Battle Rating":"776","Energy Remaining":"-1300","HP Remaining":"67"},{"Pokemon":"Pumpkaboo (Large) RL+GK/FoP","Battle Rating":"776","Energy Remaining":"-1300","HP Remaining":"67"},{"Pokemon":"Pumpkaboo (Small) RL+GK/FoP","Battle Rating":"776","Energy Remaining":"-1200","HP Remaining":"67"},{"Pokemon":"Pumpkaboo (Super) RL+GK/FoP","Battle Rating":"739","Energy Remaining":"-1400","HP Remaining":"58"},{"Pokemon":"Pupitar Bi+Dg/AP","Battle Rating":"814","Energy Remaining":"-900","HP Remaining":"76"},{"Pokemon":"Pupitar (Shadow) Bi+Dg/AP","Battle Rating":"801","Energy Remaining":"-800","HP Remaining":"73"},{"Pokemon":"Purugly SC+AA/Re","Battle Rating":"900","Energy Remaining":"-600","HP Remaining":"97"},{"Pokemon":"Purugly (Shadow) SC+AA/T","Battle Rating":"925","Energy Remaining":"-500","HP Remaining":"103"},{"Pokemon":"Pyroar I+FmC/DP","Battle Rating":"933","Energy Remaining":"-500","HP Remaining":"105"},{"Pokemon":"Quagsire MS+MB/SE","Battle Rating":"962","Energy Remaining":"-700","HP Remaining":"112"},{"Pokemon":"Quagsire (Shadow) MS+MB/SE","Battle Rating":"962","Energy Remaining":"-600","HP Remaining":"112"},{"Pokemon":"Quaquaval WA+CC/AA","Battle Rating":"958","Energy Remaining":"-500","HP Remaining":"111"},{"Pokemon":"Quaxwell WA+Li/AA","Battle Rating":"950","Energy Remaining":"-600","HP Remaining":"109"},{"Pokemon":"Quilava E+FmC/Dg","Battle Rating":"913","Energy Remaining":"-600","HP Remaining":"100"},{"Pokemon":"Quilava (Shadow) E+FmC/Dg","Battle Rating":"933","Energy Remaining":"-500","HP Remaining":"105"},{"Pokemon":"Quilladin VW+BS/EB","Battle Rating":"938","Energy Remaining":"-700","HP Remaining":"106"},{"Pokemon":"Qwilfish PSt+AT/SW","Battle Rating":"962","Energy Remaining":"-600","HP Remaining":"112"},{"Pokemon":"Qwilfish (Hisuian) PJ+AT/SB","Battle Rating":"913","Energy Remaining":"-600","HP Remaining":"100"},{"Pokemon":"Raichu VS+WC/BkB","Battle Rating":"950","Energy Remaining":"-500","HP Remaining":"109"},{"Pokemon":"Raichu (Alolan) VS+WC/GK","Battle Rating":"946","Energy Remaining":"-500","HP Remaining":"108"},{"Pokemon":"Raikou TS+WC/SB","Battle Rating":"962","Energy Remaining":"-600","HP Remaining":"112"},{"Pokemon":"Raikou (Shadow) TS+WC/SB","Battle Rating":"966","Energy Remaining":"-500","HP Remaining":"113"},{"Pokemon":"Rampardos SD+RS/Ft","Battle Rating":"876","Energy Remaining":"-600","HP Remaining":"91"},{"Pokemon":"Rampardos (Shadow) SD+RS/Ft","Battle Rating":"925","Energy Remaining":"-500","HP Remaining":"103"},{"Pokemon":"Rapidash I+DR/FmC","Battle Rating":"933","Energy Remaining":"-500","HP Remaining":"105"},{"Pokemon":"Rapidash (Galarian) FW+BS/PR","Battle Rating":"966","Energy Remaining":"-500","HP Remaining":"113"},{"Pokemon":"Raticate QA+Dg/HF","Battle Rating":"938","Energy Remaining":"-600","HP Remaining":"106"},{"Pokemon":"Raticate (Alolan) QA+Cr/Re","Battle Rating":"933","Energy Remaining":"-800","HP Remaining":"105"},{"Pokemon":"Raticate (Alolan) (Shadow) QA+Cr/HB","Battle Rating":"938","Energy Remaining":"-700","HP Remaining":"106"},{"Pokemon":"Raticate (Shadow) QA+HF/Dg","Battle Rating":"950","Energy Remaining":"-500","HP Remaining":"109"},{"Pokemon":"Rayquaza DT+BkS/DrA","Battle Rating":"938","Energy Remaining":"-500","HP Remaining":"106"},{"Pokemon":"Regice LO+Bl/Eq","Battle Rating":"966","Energy Remaining":"-800","HP Remaining":"113"},{"Pokemon":"Regice (Shadow) LO+Bl/Eq","Battle Rating":"971","Energy Remaining":"-700","HP Remaining":"114"},{"Pokemon":"Regidrago Bi+BkS/O","Battle Rating":"876","Energy Remaining":"-600","HP Remaining":"91"},{"Pokemon":"Regieleki LO+T/HB","Battle Rating":"979","Energy Remaining":"-500","HP Remaining":"116"},{"Pokemon":"Regigigas (Shadow) HPF+FB/T","Battle Rating":"975","Energy Remaining":"-500","HP Remaining":"115"},{"Pokemon":"Regirock LO+SE/FB","Battle Rating":"954","Energy Remaining":"-1200","HP Remaining":"110"},{"Pokemon":"Regirock (Shadow) LO+SE/FB","Battle Rating":"958","Energy Remaining":"-1000","HP Remaining":"111"},{"Pokemon":"Registeel LO+FB/ZC","Battle Rating":"942","Energy Remaining":"-1400","HP Remaining":"107"},{"Pokemon":"Registeel (Shadow) LO+FB/ZC","Battle Rating":"950","Energy Remaining":"-1200","HP Remaining":"109"},{"Pokemon":"Relicanth WG+AT/AP","Battle Rating":"851","Energy Remaining":"-1200","HP Remaining":"85"},{"Pokemon":"Reuniclus HPF+SB/FS","Battle Rating":"958","Energy Remaining":"-600","HP Remaining":"111"},{"Pokemon":"Rhydon MSl+BkS/S","Battle Rating":"863","Energy Remaining":"-900","HP Remaining":"88"},{"Pokemon":"Rhydon (Shadow) MSl+BkS/S","Battle Rating":"892","Energy Remaining":"-700","HP Remaining":"95"},{"Pokemon":"Rhyhorn MSl+St/Bd","Battle Rating":"876","Energy Remaining":"-1000","HP Remaining":"91"},{"Pokemon":"Rhyhorn (Shadow) MSl+St/Bd","Battle Rating":"851","Energy Remaining":"-900","HP Remaining":"85"},{"Pokemon":"Rhyperior SD+BkS/SP","Battle Rating":"851","Energy Remaining":"-900","HP Remaining":"85"},{"Pokemon":"Rhyperior (Shadow) SD+SP/BkS","Battle Rating":"884","Energy Remaining":"-700","HP Remaining":"93"},{"Pokemon":"Ribombee FW+BBu/DG","Battle Rating":"966","Energy Remaining":"-500","HP Remaining":"113"},{"Pokemon":"Roggenrola SD+SE/RB","Battle Rating":"863","Energy Remaining":"-900","HP Remaining":"88"},{"Pokemon":"Roselia PJ+SlB/PlB","Battle Rating":"933","Energy Remaining":"-500","HP Remaining":"105"},{"Pokemon":"Roserade BS+WBF/LfS","Battle Rating":"975","Energy Remaining":"-500","HP Remaining":"115"},{"Pokemon":"Rotom (Frost) TS+Tb/Bl","Battle Rating":"962","Energy Remaining":"-600","HP Remaining":"112"},{"Pokemon":"Rotom (Mow) TS+Tb/OW","Battle Rating":"962","Energy Remaining":"-600","HP Remaining":"112"},{"Pokemon":"Rotom (Wash) TS+Tb/HP","Battle Rating":"962","Energy Remaining":"-600","HP Remaining":"112"},{"Pokemon":"Rowlet L+EB/SeB","Battle Rating":"938","Energy Remaining":"-600","HP Remaining":"106"},{"Pokemon":"Rufflet WA+BrB/AA","Battle Rating":"938","Energy Remaining":"-600","HP Remaining":"106"},{"Pokemon":"Runerigus SC+ST/SB","Battle Rating":"739","Energy Remaining":"-1500","HP Remaining":"58"},{"Pokemon":"Sableye SC+FoP/Re","Battle Rating":"772","Energy Remaining":"-1400","HP Remaining":"66"},{"Pokemon":"Sableye (Shadow) SC+FoP/PG","Battle Rating":"727","Energy Remaining":"-1200","HP Remaining":"55"},{"Pokemon":"Salamence DT+O/HP","Battle Rating":"942","Energy Remaining":"-500","HP Remaining":"107"},{"Pokemon":"Salamence (Shadow) DT+O/HP","Battle Rating":"929","Energy Remaining":"-400","HP Remaining":"104"},{"Pokemon":"Salazzle I+PF/DgP","Battle Rating":"929","Energy Remaining":"-500","HP Remaining":"104"},{"Pokemon":"Samurott FC+HC/Mh","Battle Rating":"925","Energy Remaining":"-600","HP Remaining":"103"},{"Pokemon":"Sandshrew MS+Dg/RS","Battle Rating":"962","Energy Remaining":"-600","HP Remaining":"112"},{"Pokemon":"Sandshrew (Alolan) PS+NS/Bl","Battle Rating":"917","Energy Remaining":"-900","HP Remaining":"101"},{"Pokemon":"Sandshrew (Alolan) (Shadow) PS+NS/Bl","Battle Rating":"900","Energy Remaining":"-800","HP Remaining":"97"},{"Pokemon":"Sandshrew (Shadow) MS+Dg/RS","Battle Rating":"966","Energy Remaining":"-500","HP Remaining":"113"},{"Pokemon":"Sandslash MS+NS/ScS","Battle Rating":"962","Energy Remaining":"-600","HP Remaining":"112"},{"Pokemon":"Sandslash (Alolan) SC+IP/DR","Battle Rating":"855","Energy Remaining":"-1000","HP Remaining":"86"},{"Pokemon":"Sandslash (Alolan) (Shadow) SC+IP/DR","Battle Rating":"851","Energy Remaining":"-800","HP Remaining":"85"},{"Pokemon":"Sandslash (Shadow) MS+NS/ScS","Battle Rating":"950","Energy Remaining":"-600","HP Remaining":"109"},{"Pokemon":"Sandygast MS+ScS/SB","Battle Rating":"921","Energy Remaining":"-1400","HP Remaining":"102"},{"Pokemon":"Sawk PJ+BS/FB","Battle Rating":"942","Energy Remaining":"-500","HP Remaining":"107"},{"Pokemon":"Sawk (Shadow) PJ+BS/FB","Battle Rating":"933","Energy Remaining":"-500","HP Remaining":"105"},{"Pokemon":"Sawsbuck FA+WC/TBl","Battle Rating":"900","Energy Remaining":"-600","HP Remaining":"97"},{"Pokemon":"Sceptile BS+LB/Eq","Battle Rating":"975","Energy Remaining":"-500","HP Remaining":"115"},{"Pokemon":"Sceptile (Shadow) BS+LB/Eq","Battle Rating":"971","Energy Remaining":"-500","HP Remaining":"114"},{"Pokemon":"Scizor BP+XS/NS","Battle Rating":"913","Energy Remaining":"-700","HP Remaining":"100"},{"Pokemon":"Scizor (Shadow) BP+XS/NS","Battle Rating":"900","Energy Remaining":"-600","HP Remaining":"97"},{"Pokemon":"Scolipede PJ+XS/SlB","Battle Rating":"913","Energy Remaining":"-600","HP Remaining":"100"},{"Pokemon":"Scrafty C+FoP/PUP","Battle Rating":"938","Energy Remaining":"-700","HP Remaining":"106"},{"Pokemon":"Scraggy FA+FoP/BkB","Battle Rating":"888","Energy Remaining":"-600","HP Remaining":"94"},{"Pokemon":"Scyther FC+NS/XS","Battle Rating":"917","Energy Remaining":"-500","HP Remaining":"101"},{"Pokemon":"Scyther (Shadow) FC+NS/XS","Battle Rating":"917","Energy Remaining":"-500","HP Remaining":"101"},{"Pokemon":"Seadra DB+HP/Bl","Battle Rating":"900","Energy Remaining":"-600","HP Remaining":"97"},{"Pokemon":"Seadra (Shadow) DB+HP/Bl","Battle Rating":"917","Energy Remaining":"-500","HP Remaining":"101"},{"Pokemon":"Seaking PJ+DR/IW","Battle Rating":"925","Energy Remaining":"-600","HP Remaining":"103"},{"Pokemon":"Sealeo PS+BS/AB","Battle Rating":"917","Energy Remaining":"-800","HP Remaining":"101"},{"Pokemon":"Sealeo (Shadow) PS+BS/AB","Battle Rating":"938","Energy Remaining":"-700","HP Remaining":"106"},{"Pokemon":"Seel WG+AT/IW","Battle Rating":"942","Energy Remaining":"-700","HP Remaining":"107"},{"Pokemon":"Seismitoad MS+EP/SlB","Battle Rating":"962","Energy Remaining":"-700","HP Remaining":"112"},{"Pokemon":"Serperior VW+FP/AA","Battle Rating":"938","Energy Remaining":"-700","HP Remaining":"106"},{"Pokemon":"Servine VW+GK/Wr","Battle Rating":"933","Energy Remaining":"-800","HP Remaining":"105"},{"Pokemon":"Seviper PJ+Cr/PF","Battle Rating":"933","Energy Remaining":"-500","HP Remaining":"105"},{"Pokemon":"Sharpedo W+Cr/PF","Battle Rating":"938","Energy Remaining":"-400","HP Remaining":"106"},{"Pokemon":"Shaymin (Land) ZH+GK/SFl","Battle Rating":"966","Energy Remaining":"-700","HP Remaining":"113"},{"Pokemon":"Shaymin (Sky) ML+GK/EB","Battle Rating":"954","Energy Remaining":"-500","HP Remaining":"110"},{"Pokemon":"Shelgon DB+Ft/Tw","Battle Rating":"900","Energy Remaining":"-600","HP Remaining":"97"},{"Pokemon":"Shelgon (Shadow) DB+Ft/DgP","Battle Rating":"896","Energy Remaining":"-500","HP Remaining":"96"},{"Pokemon":"Shellos MSl+BS/MB","Battle Rating":"942","Energy Remaining":"-700","HP Remaining":"107"},{"Pokemon":"Shiftry Sn+LB/FoP","Battle Rating":"933","Energy Remaining":"-600","HP Remaining":"105"},{"Pokemon":"Shiftry (Shadow) Sn+LB/FoP","Battle Rating":"958","Energy Remaining":"-500","HP Remaining":"111"},{"Pokemon":"Shiinotic A+M/SeB","Battle Rating":"950","Energy Remaining":"-700","HP Remaining":"109"},{"Pokemon":"Sigilyph AS+AP/SiB","Battle Rating":"925","Energy Remaining":"-600","HP Remaining":"103"},{"Pokemon":"Simipour WG+S/Cr","Battle Rating":"917","Energy Remaining":"-500","HP Remaining":"101"},{"Pokemon":"Simisage VW+GK/Cr","Battle Rating":"950","Energy Remaining":"-500","HP Remaining":"109"},{"Pokemon":"Simisear FS+Cr/Ft","Battle Rating":"958","Energy Remaining":"-500","HP Remaining":"111"},{"Pokemon":"Sirfetch'd C+LB/NS","Battle Rating":"950","Energy Remaining":"-500","HP Remaining":"109"},{"Pokemon":"Skarmory AS+BrB/SA","Battle Rating":"867","Energy Remaining":"-1200","HP Remaining":"89"},{"Pokemon":"Skarmory (Shadow) AS+BrB/SA","Battle Rating":"888","Energy Remaining":"-1000","HP Remaining":"94"},{"Pokemon":"Skeledirge I+SB/DV","Battle Rating":"884","Energy Remaining":"-1400","HP Remaining":"93"},{"Pokemon":"Skiddo RSm+RS/SeB","Battle Rating":"958","Energy Remaining":"-600","HP Remaining":"111"},{"Pokemon":"Skorupi PSt+CP/AT","Battle Rating":"962","Energy Remaining":"-700","HP Remaining":"112"},{"Pokemon":"Skorupi (Shadow) PSt+CP/AT","Battle Rating":"962","Energy Remaining":"-600","HP Remaining":"112"},{"Pokemon":"Skrelp WG+AT/SlB","Battle Rating":"925","Energy Remaining":"-600","HP Remaining":"103"},{"Pokemon":"Skuntank PJ+Cr/TBl","Battle Rating":"913","Energy Remaining":"-600","HP Remaining":"100"},{"Pokemon":"Skuntank (Shadow) PJ+Cr/TBl","Battle Rating":"933","Energy Remaining":"-500","HP Remaining":"105"},{"Pokemon":"Slaking Y+BS/Eq","Battle Rating":"995","Energy Remaining":"-500","HP Remaining":"120"},{"Pokemon":"Sliggoo WG+MW/DgP","Battle Rating":"913","Energy Remaining":"-700","HP Remaining":"100"},{"Pokemon":"Slowbro WG+S/IB","Battle Rating":"913","Energy Remaining":"-700","HP Remaining":"100"},{"Pokemon":"Slowbro (Galarian) PJ+S/P","Battle Rating":"913","Energy Remaining":"-700","HP Remaining":"100"},{"Pokemon":"Slowbro (Shadow) WG+S/IB","Battle Rating":"900","Energy Remaining":"-600","HP Remaining":"97"},{"Pokemon":"Slowking WG+S/P","Battle Rating":"913","Energy Remaining":"-700","HP Remaining":"100"},{"Pokemon":"Slowking (Galarian) H+S/SB","Battle Rating":"933","Energy Remaining":"-700","HP Remaining":"105"},{"Pokemon":"Slowking (Shadow) WG+S/P","Battle Rating":"900","Energy Remaining":"-600","HP Remaining":"97"},{"Pokemon":"Slowpoke Cf+Psh/WP","Battle Rating":"966","Energy Remaining":"-700","HP Remaining":"113"},{"Pokemon":"Slowpoke (Galarian) Cf+S/Psh","Battle Rating":"966","Energy Remaining":"-700","HP Remaining":"113"},{"Pokemon":"Slowpoke (Shadow) Cf+Psh/WP","Battle Rating":"958","Energy Remaining":"-600","HP Remaining":"111"},{"Pokemon":"Slurpuff Ch+Ft/EB","Battle Rating":"884","Energy Remaining":"-700","HP Remaining":"93"},{"Pokemon":"Smoochum PS+IP/Psh","Battle Rating":"950","Energy Remaining":"-500","HP Remaining":"109"},{"Pokemon":"Sneasel IS+Av/FoP","Battle Rating":"958","Energy Remaining":"-500","HP Remaining":"111"},{"Pokemon":"Sneasel (Hisuian) PJ+CC/AA","Battle Rating":"933","Energy Remaining":"-500","HP Remaining":"105"},{"Pokemon":"Sneasel (Hisuian) (Shadow) PJ+CC/AA","Battle Rating":"925","Energy Remaining":"-500","HP Remaining":"103"},{"Pokemon":"Sneasel (Shadow) IS+Av/FoP","Battle Rating":"954","Energy Remaining":"-500","HP Remaining":"110"},{"Pokemon":"Sneasler SC+CC/AA","Battle Rating":"925","Energy Remaining":"-500","HP Remaining":"103"},{"Pokemon":"Sneasler (Shadow) SC+CC/AA","Battle Rating":"909","Energy Remaining":"-400","HP Remaining":"99"},{"Pokemon":"Snorlax L+BS/SP","Battle Rating":"867","Energy Remaining":"-800","HP Remaining":"89"},{"Pokemon":"Snorlax (Shadow) L+BS/SP","Battle Rating":"884","Energy Remaining":"-700","HP Remaining":"93"},{"Pokemon":"Snover PS+IB/EB","Battle Rating":"938","Energy Remaining":"-600","HP Remaining":"106"},{"Pokemon":"Snover (Shadow) PS+IB/EB","Battle Rating":"958","Energy Remaining":"-500","HP Remaining":"111"},{"Pokemon":"Snubbull Tk+Cr/BkB","Battle Rating":"938","Energy Remaining":"-500","HP Remaining":"106"},{"Pokemon":"Snubbull (Shadow) Tk+Cr/BkB","Battle Rating":"938","Energy Remaining":"-500","HP Remaining":"106"},{"Pokemon":"Solosis HPP+Psh/T","Battle Rating":"971","Energy Remaining":"-500","HP Remaining":"114"},{"Pokemon":"Solrock Cf+RS/P","Battle Rating":"925","Energy Remaining":"-900","HP Remaining":"103"},{"Pokemon":"Spinda PC+IW/Dg","Battle Rating":"975","Energy Remaining":"-700","HP Remaining":"115"},{"Pokemon":"Spiritomb SkP+SB/SS","Battle Rating":"801","Energy Remaining":"-1300","HP Remaining":"73"},{"Pokemon":"Spoink ZH+SB/Re","Battle Rating":"958","Energy Remaining":"-700","HP Remaining":"111"},{"Pokemon":"Spoink (Shadow) ZH+SB/MrC","Battle Rating":"950","Energy Remaining":"-600","HP Remaining":"109"},{"Pokemon":"Spritzee Ch+Tb/DK","Battle Rating":"900","Energy Remaining":"-700","HP Remaining":"97"},{"Pokemon":"Stantler Tk+WC/St","Battle Rating":"925","Energy Remaining":"-600","HP Remaining":"103"},{"Pokemon":"Stantler (Shadow) Tk+WC/St","Battle Rating":"917","Energy Remaining":"-500","HP Remaining":"101"},{"Pokemon":"Staraptor WA+BrB/CC","Battle Rating":"950","Energy Remaining":"-500","HP Remaining":"109"},{"Pokemon":"Staraptor (Shadow) WA+BrB/CC","Battle Rating":"942","Energy Remaining":"-500","HP Remaining":"107"},{"Pokemon":"Staravia WA+BrB/AA","Battle Rating":"958","Energy Remaining":"-500","HP Remaining":"111"},{"Pokemon":"Staravia (Shadow) WA+BrB/AA","Battle Rating":"950","Energy Remaining":"-500","HP Remaining":"109"},{"Pokemon":"Starmie QA+P/IB","Battle Rating":"938","Energy Remaining":"-600","HP Remaining":"106"},{"Pokemon":"Steelix DT+BkS/Eq","Battle Rating":"867","Energy Remaining":"-1300","HP Remaining":"89"},{"Pokemon":"Steelix (Shadow) DT+BkS/Eq","Battle Rating":"876","Energy Remaining":"-1100","HP Remaining":"91"},{"Pokemon":"Stoutland L+WC/Cr","Battle Rating":"900","Energy Remaining":"-600","HP Remaining":"97"},{"Pokemon":"Stufful Tk+SP/St","Battle Rating":"925","Energy Remaining":"-600","HP Remaining":"103"},{"Pokemon":"Stunfisk TS+MB/D","Battle Rating":"950","Energy Remaining":"-800","HP Remaining":"109"},{"Pokemon":"Stunfisk (Galarian) MS+RS/Eq","Battle Rating":"925","Energy Remaining":"-1300","HP Remaining":"103"},{"Pokemon":"Stunky Bi+Cr/SlB","Battle Rating":"851","Energy Remaining":"-600","HP Remaining":"85"},{"Pokemon":"Stunky (Shadow) Bi+Cr/SlB","Battle Rating":"855","Energy Remaining":"-500","HP Remaining":"86"},{"Pokemon":"Sudowoodo C+MeB/RS","Battle Rating":"917","Energy Remaining":"-1000","HP Remaining":"101"},{"Pokemon":"Sudowoodo (Shadow) C+RS/MeB","Battle Rating":"917","Energy Remaining":"-800","HP Remaining":"101"},{"Pokemon":"Suicune Sn+BuB/HP","Battle Rating":"950","Energy Remaining":"-800","HP Remaining":"109"},{"Pokemon":"Suicune (Shadow) Sn+BuB/HP","Battle Rating":"942","Energy Remaining":"-700","HP Remaining":"107"},{"Pokemon":"Sunflora BS+LfS/SlB","Battle Rating":"958","Energy Remaining":"-600","HP Remaining":"111"},{"Pokemon":"Swadloon BBi+EB/SvW","Battle Rating":"867","Energy Remaining":"-800","HP Remaining":"89"},{"Pokemon":"Swalot MS+SlB/IB","Battle Rating":"966","Energy Remaining":"-800","HP Remaining":"113"},{"Pokemon":"Swampert MS+HC/Eq","Battle Rating":"962","Energy Remaining":"-600","HP Remaining":"112"},{"Pokemon":"Swampert (Shadow) MS+HC/Eq","Battle Rating":"966","Energy Remaining":"-500","HP Remaining":"113"},{"Pokemon":"Swanna AS+Hu/IB","Battle Rating":"925","Energy Remaining":"-600","HP Remaining":"103"},{"Pokemon":"Swanna (Shadow) WG+Hu/IB","Battle Rating":"917","Energy Remaining":"-500","HP Remaining":"101"},{"Pokemon":"Swellow WA+BrB/AA","Battle Rating":"950","Energy Remaining":"-500","HP Remaining":"109"},{"Pokemon":"Swirlix Tk+EB/DK","Battle Rating":"942","Energy Remaining":"-700","HP Remaining":"107"},{"Pokemon":"Swoobat Cf+PsF/AA","Battle Rating":"958","Energy Remaining":"-600","HP Remaining":"111"},{"Pokemon":"Sylveon Ch+M/Psh","Battle Rating":"884","Energy Remaining":"-700","HP Remaining":"93"},{"Pokemon":"Talonflame I+BrB/FmC","Battle Rating":"942","Energy Remaining":"-600","HP Remaining":"107"},{"Pokemon":"Tangela VW+GK/SlB","Battle Rating":"938","Energy Remaining":"-600","HP Remaining":"106"},{"Pokemon":"Tangela (Shadow) VW+GK/SlB","Battle Rating":"950","Energy Remaining":"-500","HP Remaining":"109"},{"Pokemon":"Tangrowth VW+PW/RS","Battle Rating":"938","Energy Remaining":"-600","HP Remaining":"106"},{"Pokemon":"Tangrowth (Shadow) VW+PW/RS","Battle Rating":"925","Energy Remaining":"-600","HP Remaining":"103"},{"Pokemon":"Tapu Fini WG+S/M","Battle Rating":"913","Energy Remaining":"-700","HP Remaining":"100"},{"Pokemon":"Tauros Tk+HA/TBl","Battle Rating":"925","Energy Remaining":"-600","HP Remaining":"103"},{"Pokemon":"Teddiursa L+CrC/Cr","Battle Rating":"900","Energy Remaining":"-600","HP Remaining":"97"},{"Pokemon":"Teddiursa (Shadow) L+CrC/Cr","Battle Rating":"896","Energy Remaining":"-500","HP Remaining":"96"},{"Pokemon":"Tentacool B+Wr/BuB","Battle Rating":"958","Energy Remaining":"-700","HP Remaining":"111"},{"Pokemon":"Tentacruel PJ+AS/Sc","Battle Rating":"925","Energy Remaining":"-700","HP Remaining":"103"},{"Pokemon":"Throh LK+BS/FB","Battle Rating":"962","Energy Remaining":"-700","HP Remaining":"112"},{"Pokemon":"Throh (Shadow) LK+BS/FB","Battle Rating":"962","Energy Remaining":"-600","HP Remaining":"112"},{"Pokemon":"Timburr LK+BkB/RT","Battle Rating":"962","Energy Remaining":"-600","HP Remaining":"112"},{"Pokemon":"Tirtouga WG+S/BS","Battle Rating":"876","Energy Remaining":"-1000","HP Remaining":"91"},{"Pokemon":"Togedemaru TS+FeS/WC","Battle Rating":"950","Energy Remaining":"-800","HP Remaining":"109"},{"Pokemon":"Togekiss Ch+AP/AuS","Battle Rating":"884","Energy Remaining":"-600","HP Remaining":"93"},{"Pokemon":"Togetic FW+AA/DG","Battle Rating":"962","Energy Remaining":"-700","HP Remaining":"112"},{"Pokemon":"Torkoal FS+Ov/Eq","Battle Rating":"933","Energy Remaining":"-800","HP Remaining":"105"},{"Pokemon":"Torracat E+FmC/Cr","Battle Rating":"933","Energy Remaining":"-500","HP Remaining":"105"},{"Pokemon":"Torterra RL+FP/SE","Battle Rating":"888","Energy Remaining":"-600","HP Remaining":"94"},{"Pokemon":"Torterra (Shadow) RL+FP/SE","Battle Rating":"863","Energy Remaining":"-600","HP Remaining":"88"},{"Pokemon":"Totodile WG+Cr/AJ","Battle Rating":"925","Energy Remaining":"-600","HP Remaining":"103"},{"Pokemon":"Totodile (Shadow) WG+Cr/AJ","Battle Rating":"938","Energy Remaining":"-500","HP Remaining":"106"},{"Pokemon":"Toucannon BS+DrlP/RB","Battle Rating":"979","Energy Remaining":"-500","HP Remaining":"116"},{"Pokemon":"Toxapex PJ+Bri/SW","Battle Rating":"896","Energy Remaining":"-1000","HP Remaining":"96"},{"Pokemon":"Toxicroak C+MB/SlB","Battle Rating":"950","Energy Remaining":"-500","HP Remaining":"109"},{"Pokemon":"Tranquill AS+AA/SA","Battle Rating":"925","Energy Remaining":"-600","HP Remaining":"103"},{"Pokemon":"Trapinch MS+ScS/Cr","Battle Rating":"966","Energy Remaining":"-500","HP Remaining":"113"},{"Pokemon":"Trapinch (Shadow) MS+ScS/Cr","Battle Rating":"966","Energy Remaining":"-400","HP Remaining":"113"},{"Pokemon":"Trevenant SC+SeB/SB","Battle Rating":"752","Energy Remaining":"-1200","HP Remaining":"61"},{"Pokemon":"Tropius AS+LB/AA","Battle Rating":"913","Energy Remaining":"-900","HP Remaining":"100"},{"Pokemon":"Trumbeak Pk+DrlP/RB","Battle Rating":"942","Energy Remaining":"-500","HP Remaining":"107"},{"Pokemon":"Tsareena ML+GK/TAx","Battle Rating":"917","Energy Remaining":"-600","HP Remaining":"101"},{"Pokemon":"Turtonator I+DgP/Ov","Battle Rating":"946","Energy Remaining":"-700","HP Remaining":"108"},{"Pokemon":"Turtwig RL+BS/EB","Battle Rating":"888","Energy Remaining":"-600","HP Remaining":"94"},{"Pokemon":"Turtwig (Shadow) RL+BS/EB","Battle Rating":"909","Energy Remaining":"-500","HP Remaining":"99"},{"Pokemon":"Typhlosion I+BB/SoB","Battle Rating":"938","Energy Remaining":"-600","HP Remaining":"106"},{"Pokemon":"Typhlosion (Shadow) I+BB/SoB","Battle Rating":"925","Energy Remaining":"-500","HP Remaining":"103"},{"Pokemon":"Tyranitar SD+BrS/SE","Battle Rating":"900","Energy Remaining":"-800","HP Remaining":"97"},{"Pokemon":"Tyranitar (Shadow) SD+BrS/SE","Battle Rating":"884","Energy Remaining":"-700","HP Remaining":"93"},{"Pokemon":"Tyrantrum DT+MeB/Cr","Battle Rating":"892","Energy Remaining":"-800","HP Remaining":"95"},{"Pokemon":"Tyrunt DT+DC/AP","Battle Rating":"838","Energy Remaining":"-900","HP Remaining":"82"},{"Pokemon":"Umbreon Sn+FoP/LR","Battle Rating":"925","Energy Remaining":"-1000","HP Remaining":"103"},{"Pokemon":"Unfezant AS+SA/HB","Battle Rating":"958","Energy Remaining":"-500","HP Remaining":"111"},{"Pokemon":"Unown HPP+Str","Battle Rating":"975","Energy Remaining":"-500","HP Remaining":"115"},{"Pokemon":"Ursaluna Tk+TP/HH","Battle Rating":"925","Energy Remaining":"-600","HP Remaining":"103"},{"Pokemon":"Ursaluna (Shadow) Tk+TP/HH","Battle Rating":"917","Energy Remaining":"-500","HP Remaining":"101"},{"Pokemon":"Ursaring C+CC/TBl","Battle Rating":"958","Energy Remaining":"-500","HP Remaining":"111"},{"Pokemon":"Ursaring (Shadow) C+CC/TBl","Battle Rating":"950","Energy Remaining":"-500","HP Remaining":"109"},{"Pokemon":"Uxie Cf+FS/T","Battle Rating":"933","Energy Remaining":"-800","HP Remaining":"105"},{"Pokemon":"Vanillish FB+IW/SiB","Battle Rating":"913","Energy Remaining":"-600","HP Remaining":"100"},{"Pokemon":"Vanilluxe FB+Bl/SiB","Battle Rating":"913","Energy Remaining":"-600","HP Remaining":"100"},{"Pokemon":"Vaporeon WG+AT/LR","Battle Rating":"913","Energy Remaining":"-700","HP Remaining":"100"},{"Pokemon":"Venomoth Inf+PF/BBu","Battle Rating":"917","Energy Remaining":"-600","HP Remaining":"101"},{"Pokemon":"Venomoth (Shadow) Inf+PF/BBu","Battle Rating":"954","Energy Remaining":"-500","HP Remaining":"110"},{"Pokemon":"Venusaur VW+FP/SlB","Battle Rating":"938","Energy Remaining":"-600","HP Remaining":"106"},{"Pokemon":"Venusaur (Shadow) VW+FP/SlB","Battle Rating":"925","Energy Remaining":"-600","HP Remaining":"103"},{"Pokemon":"Vespiquen FC+XS/PG","Battle Rating":"913","Energy Remaining":"-700","HP Remaining":"100"},{"Pokemon":"Vibrava MS+ST/BBu","Battle Rating":"975","Energy Remaining":"-500","HP Remaining":"115"},{"Pokemon":"Vibrava (Shadow) MS+ST/BBu","Battle Rating":"966","Energy Remaining":"-500","HP Remaining":"113"},{"Pokemon":"Victini QA+VC/P","Battle Rating":"950","Energy Remaining":"-600","HP Remaining":"109"},{"Pokemon":"Victreebel RL+LB/AS","Battle Rating":"909","Energy Remaining":"-500","HP Remaining":"99"},{"Pokemon":"Victreebel (Shadow) RL+LB/AS","Battle Rating":"892","Energy Remaining":"-500","HP Remaining":"95"},{"Pokemon":"Vigoroth C+BS/Bd","Battle Rating":"950","Energy Remaining":"-700","HP Remaining":"109"},{"Pokemon":"Vikavolt VS+XS/D","Battle Rating":"942","Energy Remaining":"-500","HP Remaining":"107"},{"Pokemon":"Vileplume RL+SlB/PlB","Battle Rating":"876","Energy Remaining":"-600","HP Remaining":"91"},{"Pokemon":"Vileplume (Shadow) RL+SlB/M","Battle Rating":"900","Energy Remaining":"-500","HP Remaining":"97"},{"Pokemon":"Vivillon G+AA/BBu","Battle Rating":"933","Energy Remaining":"-600","HP Remaining":"105"},{"Pokemon":"Volbeat Tk+BBu/Tb","Battle Rating":"913","Energy Remaining":"-700","HP Remaining":"100"},{"Pokemon":"Volcarona FS+Ov/BBu","Battle Rating":"958","Energy Remaining":"-500","HP Remaining":"111"},{"Pokemon":"Vullaby AS+BrB/FoP","Battle Rating":"942","Energy Remaining":"-800","HP Remaining":"107"},{"Pokemon":"Wailmer WG+BS/HS","Battle Rating":"913","Energy Remaining":"-700","HP Remaining":"100"},{"Pokemon":"Wailmer (Shadow) WG+BS/HS","Battle Rating":"900","Energy Remaining":"-600","HP Remaining":"97"},{"Pokemon":"Wailord WG+S/Bl","Battle Rating":"913","Energy Remaining":"-700","HP Remaining":"100"},{"Pokemon":"Wailord (Shadow) WG+S/Bl","Battle Rating":"900","Energy Remaining":"-600","HP Remaining":"97"},{"Pokemon":"Walrein PS+ISp/Eq","Battle Rating":"938","Energy Remaining":"-700","HP Remaining":"106"},{"Pokemon":"Walrein (Shadow) PS+ISp/Eq","Battle Rating":"925","Energy Remaining":"-600","HP Remaining":"103"},{"Pokemon":"Wartortle WG+IB/HP","Battle Rating":"900","Energy Remaining":"-800","HP Remaining":"97"},{"Pokemon":"Wartortle (Shadow) WG+IB/HP","Battle Rating":"913","Energy Remaining":"-700","HP Remaining":"100"},{"Pokemon":"Watchog Bi+Cr/GK","Battle Rating":"851","Energy Remaining":"-600","HP Remaining":"85"},{"Pokemon":"Watchog (Shadow) Bi+Cr/GK","Battle Rating":"855","Energy Remaining":"-500","HP Remaining":"86"},{"Pokemon":"Weavile Sn+Av/FoP","Battle Rating":"962","Energy Remaining":"-500","HP Remaining":"112"},{"Pokemon":"Weavile (Shadow) Sn+Av/FoP","Battle Rating":"954","Energy Remaining":"-400","HP Remaining":"110"},{"Pokemon":"Weepinbell BS+PW/SlB","Battle Rating":"975","Energy Remaining":"-500","HP Remaining":"115"},{"Pokemon":"Weepinbell (Shadow) BS+PW/SlB","Battle Rating":"971","Energy Remaining":"-500","HP Remaining":"114"},{"Pokemon":"Weezing Inf+SlB/SB","Battle Rating":"942","Energy Remaining":"-700","HP Remaining":"107"},{"Pokemon":"Weezing (Galarian) FW+PR/BrS","Battle Rating":"962","Energy Remaining":"-700","HP Remaining":"112"},{"Pokemon":"Weezing (Shadow) Inf+SlB/SB","Battle Rating":"925","Energy Remaining":"-600","HP Remaining":"103"},{"Pokemon":"Whimsicott FW+SeB/M","Battle Rating":"962","Energy Remaining":"-700","HP Remaining":"112"},{"Pokemon":"Whirlipede PSt+SlB/SiB","Battle Rating":"962","Energy Remaining":"-700","HP Remaining":"112"},{"Pokemon":"Whiscash MS+MB/Bl","Battle Rating":"950","Energy Remaining":"-800","HP Remaining":"109"},{"Pokemon":"Whiscash (Shadow) MS+MB/Bl","Battle Rating":"962","Energy Remaining":"-700","HP Remaining":"112"},{"Pokemon":"Wigglytuff Ch+IB/DV","Battle Rating":"892","Energy Remaining":"-700","HP Remaining":"95"},{"Pokemon":"Wobbuffet C+Re/MrC","Battle Rating":"950","Energy Remaining":"-1300","HP Remaining":"109"},{"Pokemon":"Wobbuffet (Shadow) C+MrC/F","Battle Rating":"938","Energy Remaining":"-1100","HP Remaining":"106"},{"Pokemon":"Wormadam (Plant) BBi+EB/BBu","Battle Rating":"884","Energy Remaining":"-700","HP Remaining":"93"},{"Pokemon":"Wormadam (Sandy) BBi+BBu/Bd","Battle Rating":"884","Energy Remaining":"-700","HP Remaining":"93"},{"Pokemon":"Wormadam (Trash) Cf+BBu/IH","Battle Rating":"913","Energy Remaining":"-1200","HP Remaining":"100"},{"Pokemon":"Xatu AS+AA/FS","Battle Rating":"925","Energy Remaining":"-600","HP Remaining":"103"},{"Pokemon":"Xatu (Shadow) AS+AA/FS","Battle Rating":"954","Energy Remaining":"-500","HP Remaining":"110"},{"Pokemon":"Yanma WA+AA/SvW","Battle Rating":"938","Energy Remaining":"-600","HP Remaining":"106"},{"Pokemon":"Yanmega WA+AA/BBu","Battle Rating":"950","Energy Remaining":"-500","HP Remaining":"109"},{"Pokemon":"Zangoose SC+CC/NS","Battle Rating":"925","Energy Remaining":"-500","HP Remaining":"103"},{"Pokemon":"Zapdos TS+DrlP/T","Battle Rating":"966","Energy Remaining":"-500","HP Remaining":"113"},{"Pokemon":"Zapdos (Galarian) C+AP/BrB","Battle Rating":"950","Energy Remaining":"-500","HP Remaining":"109"},{"Pokemon":"Zapdos (Shadow) TS+DrlP/Tb","Battle Rating":"966","Energy Remaining":"-500","HP Remaining":"113"},{"Pokemon":"Zebstrika Sp+WC/FmC","Battle Rating":"942","Energy Remaining":"-500","HP Remaining":"107"},{"Pokemon":"Zebstrika (Shadow) Sp+WC/FmC","Battle Rating":"933","Energy Remaining":"-500","HP Remaining":"105"},{"Pokemon":"Zoroark SC+FoP/SlB","Battle Rating":"917","Energy Remaining":"-400","HP Remaining":"101"},{"Pokemon":"Zweilous DB+BS/DP","Battle Rating":"900","Energy Remaining":"-600","HP Remaining":"97"},{"Pokemon":"Zygarde (10% Forme) DT+Cr/Eq","Battle Rating":"942","Energy Remaining":"-500","HP Remaining":"107"},{"Pokemon":"Zygarde (50% Forme) DT+Cr/Eq","Battle Rating":"909","Energy Remaining":"-700","HP Remaining":"99"}]